[
  {
    "page_number": 0,
    "bbox": [
      108.48,
      716.72,
      305.76,
      737.01
    ],
    "text": ",ytr tpepNahfj;jpw;fhf106",
    "fonts": [
      "Kalaham",
      "Times-Roman"
    ],
    "sizes": [
      8.00001335144043,
      12.000008583068848
    ]
  },
  {
    "page_number": 0,
    "bbox": [
      108.48,
      507.93,
      252.81,
      577.53
    ],
    "text": "NkNyAs;s cUitg;ghUq;fs;. mq;F gyu;gy;NtW nraw;ghLfspy;<Lgl;Lf; nfhz;bUg;gijf;fhz;fpwPh;fs;.",
    "fonts": [
      "Kalaham"
    ],
    "sizes": [
      12.000008583068848
    ]
  },
  {
    "page_number": 0,
    "bbox": [
      108.48,
      594.33,
      252.7,
      692.73
    ],
    "text": "mtu;fs; jkJ nraw;ghLfspy; tpidj;jpwDld;<LgLtjw;F mth;fSf;Fr;rf;jp mtrpakhfpd;wJ. ,r;rf;jpia mtu;fs; vt;thWngw;Wf;nfhs;fpd;wdu;? rw;Wr;rpe;jpj;Jg; ghUq;fs;.",
    "fonts": [
      "Kalaham"
    ],
    "sizes": [
      12.000008583068848
    ]
  },
  {
    "page_number": 0,
    "bbox": [
      358.2,
      692.25,
      400.92,
      704.25
    ],
    "text": "cU 8.1",
    "fonts": [
      "Kalaham"
    ],
    "sizes": [
      12.000008583068848
    ]
  },
  {
    "page_number": 0,
    "bbox": [
      262.92,
      566.53,
      402.59,
      591.45
    ],
    "text": "fdpAg;Gfs;Nghrizg;nghUs;fs;",
    "fonts": [
      "Kalaham"
    ],
    "sizes": [
      11.000007629394531
    ]
  },
  {
    "page_number": 0,
    "bbox": [
      337.8,
      496.21,
      421.79,
      507.21
    ],
    "text": "fhNghitjNuw;W",
    "fonts": [
      "Kalaham"
    ],
    "sizes": [
      11.000007629394531
    ]
  },
  {
    "page_number": 0,
    "bbox": [
      437.76,
      571.09,
      479.75,
      582.09
    ],
    "text": "nfhOg;G",
    "fonts": [
      "Kalaham"
    ],
    "sizes": [
      11.000007629394531
    ]
  },
  {
    "page_number": 0,
    "bbox": [
      284.88,
      643.69,
      451.32,
      656.97
    ],
    "text": "Gujk;tpw;wkpd;fs;",
    "fonts": [
      "Kalaham"
    ],
    "sizes": [
      11.000007629394531
    ]
  },
  {
    "page_number": 0,
    "bbox": [
      138.84,
      150.07,
      178.25,
      187.86
    ],
    "text": "08",
    "fonts": [
      "FMGanganee"
    ],
    "sizes": [
      37.794212341308594
    ]
  },
  {
    "page_number": 0,
    "bbox": [
      186.15,
      149.68,
      477.84,
      198.74
    ],
    "text": "ey;Y}l;lj;jpw;F Vw;Gila czTg;ey;Y}l;lj;jpw;F Vw;Gila czTg;ey;Y}l;lj;jpw;F Vw;Gila czTg;ey;Y}l;lj;jpw;F Vw;Gila czTg;ey;Y}l;lj;jpw;F Vw;Gila czTg;gof;fq;fisf; iff;nfhs;Nthk;gof;fq;fisf; iff;nfhs;Nthk;gof;fq;fisf; iff;nfhs;Nthk;gof;fq;fisf; iff;nfhs;Nthk;gof;fq;fisf; iff;nfhs;Nthk;",
    "fonts": [
      "Kalyani"
    ],
    "sizes": [
      22.000015258789062
    ]
  },
  {
    "page_number": 1,
    "bbox": [
      287.76,
      716.12,
      487.64,
      738.45
    ],
    "text": ",ytr tpepNahfj;jpw;fhf107",
    "fonts": [
      "Kalaham",
      "Times-Roman"
    ],
    "sizes": [
      8.00001335144043,
      12.000008583068848
    ]
  },
  {
    "page_number": 1,
    "bbox": [
      108.48,
      133.53,
      486.66,
      260.73
    ],
    "text": "vkJ clypd; nraw;ghLfs; Xu; ,ae;jpuj;jpd; njhopw;ghLfisxj;jitahFk;. ,ae;jpuj;jpd; njhopw;ghl;Lf;F vupnghUs; Njitg;gLfpwJ.vupnghUs; jfdkiltjd; %yk; ,ae;jpuj;Jf;Fj; Njitahd rf;jpfpilf;fg;ngWk; vd;gij ePq;fs; Vw;fdNt mwpe;J itj;Js;sPu;fs;. vkJclypd; njhopw;ghLfSf;Fj; Njitahd rf;jp vt;thW fpilf;fg;ngWfpd;wJ? ehk; cz;Zk; cztpypUe;Nj rf;jp fpilf;fpd;wJ vd;gijcq;fshy; re;Njfkpd;wpf; $wKbAk;. ePq;fs; 6> 7> 8 Mk; juq;fspy;fw;w czT tiffisAk; mt;TzT tiffspy; mlq;fpAs;s Nghrizg;nghUs;fs; gw;wpAk; Qhgfg;gLj;jpg; ghUq;fs;.",
    "fonts": [
      "Kalaham"
    ],
    "sizes": [
      12.000008583068848
    ]
  },
  {
    "page_number": 1,
    "bbox": [
      108.48,
      273.09,
      486.67,
      313.89
    ],
    "text": "vkJ clYf;Fj; Njitahd vy;yhg; Nghrizg; nghUs;fSk;(Cl;lr;rj;JfSk;) Njitahd mstpy; mlq;fpAs;s czT epiw czTepiw czTepiw czTepiw czTepiw czTvd ePq;fs; Kd;ida tFg;Gfspy; fw;W ,Ug;gPu;fs;.",
    "fonts": [
      "Kalaham"
    ],
    "sizes": [
      12.000008583068848
    ]
  },
  {
    "page_number": 1,
    "bbox": [
      126.48,
      402.69,
      479.77,
      429.09
    ],
    "text": "ePq;fs; jahhpj;j ml;ltizapy;> fPNo jug;gl;Ls;s Fw;wpthpg;glj;jpy;cs;s tplaq;fs; mlq;fpAs;sdth vd xg;gpl;Lg; ghUq;fs;.",
    "fonts": [
      "Kalaham"
    ],
    "sizes": [
      12.000008583068848
    ]
  },
  {
    "page_number": 1,
    "bbox": [
      108.48,
      676.29,
      486.47,
      702.69
    ],
    "text": "taJ> Mz; - ngz; ghy; NtWghL vd;gtw;Wf;F mikthfxUtu; ngw;Wf;nfhs;Sk; cztpd; msTk; Njitg;gLk; Nghrizg;",
    "fonts": [
      "Kalaham"
    ],
    "sizes": [
      12.000008583068848
    ]
  },
  {
    "page_number": 1,
    "bbox": [
      124.86,
      332.55,
      205.5,
      344.91
    ],
    "text": "nraw;ghL 8.1nraw;ghL 8.1nraw;ghL 8.1nraw;ghL 8.1nraw;ghL 8.1",
    "fonts": [
      "Kalaham"
    ],
    "sizes": [
      12.000008583068848
    ]
  },
  {
    "page_number": 1,
    "bbox": [
      125.04,
      353.13,
      473.47,
      379.53
    ],
    "text": "Vw;fdNt fw;w mwpitg; gad;gLj;jp kdpjDf;F cztpdhy;fpilf;Fk; gad;fis ml;ltizg;gLj;Jq;fs;.",
    "fonts": [
      "Kalaham"
    ],
    "sizes": [
      11.000007629394531,
      12.000008583068848
    ]
  },
  {
    "page_number": 1,
    "bbox": [
      276.6,
      549.33,
      345.11,
      575.73
    ],
    "text": "cztpd;Kf;fpaj;Jtk;",
    "fonts": [
      "Kalaham"
    ],
    "sizes": [
      12.000008583068848
    ]
  },
  {
    "page_number": 1,
    "bbox": [
      113.28,
      516.33,
      464.14,
      571.53
    ],
    "text": "caph;tho;tjw;Fmd;whl Ntiyfisr;nra;tjw;Fj; Njitahdrf;jpiag; ngw;Wf;nfhs;s",
    "fonts": [
      "Kalaham"
    ],
    "sizes": [
      12.000008583068848
    ]
  },
  {
    "page_number": 1,
    "bbox": [
      346.08,
      608.73,
      452.79,
      635.13
    ],
    "text": "gy;NtW XNkhd;fspd;cw;gj;jpf;F",
    "fonts": [
      "Kalaham"
    ],
    "sizes": [
      12.000008583068848
    ]
  },
  {
    "page_number": 1,
    "bbox": [
      389.88,
      573.93,
      482.87,
      585.93
    ],
    "text": "cly; tsu;r;rpf;F",
    "fonts": [
      "Kalaham"
    ],
    "sizes": [
      12.000008583068848
    ]
  },
  {
    "page_number": 1,
    "bbox": [
      115.68,
      460.89,
      484.19,
      514.29
    ],
    "text": "Neha;f;fpUkpfspypUe;Jcliyg; ghJfhj;jy;Gjpa fyq;fspdJk;,ioaq;fspdJk; tsu;r;rpf;Fk;GJg;gpj;jYf;Fk;",
    "fonts": [
      "Kalaham"
    ],
    "sizes": [
      11.000007629394531,
      12.000008583068848
    ]
  },
  {
    "page_number": 1,
    "bbox": [
      114.72,
      590.73,
      235.42,
      617.13
    ],
    "text": "cly; ntg;gepiyiag;NgZtjw;F",
    "fonts": [
      "Kalaham"
    ],
    "sizes": [
      12.000008583068848
    ]
  },
  {
    "page_number": 1,
    "bbox": [
      174.24,
      640.89,
      256.68,
      652.89
    ],
    "text": "NtW Njitfs;",
    "fonts": [
      "Kalaham"
    ],
    "sizes": [
      12.000008583068848
    ]
  },
  {
    "page_number": 1,
    "bbox": [
      249.12,
      438.45,
      327.82,
      464.85
    ],
    "text": "MNuhf;fpakhftho;tjw;F",
    "fonts": [
      "Kalaham"
    ],
    "sizes": [
      12.000008583068848
    ]
  },
  {
    "page_number": 2,
    "bbox": [
      108.48,
      716.72,
      305.76,
      737.01
    ],
    "text": ",ytr tpepNahfj;jpw;fhf108",
    "fonts": [
      "Kalaham",
      "Times-Roman"
    ],
    "sizes": [
      8.00001335144043,
      12.000008583068848
    ]
  },
  {
    "page_number": 2,
    "bbox": [
      108.48,
      133.53,
      486.45,
      188.73
    ],
    "text": "nghUs;fspd; msTk; NtWgLtij ePq;fs; mwptPu;fsh? fPNo jug;gl;Ls;stupg;glj;jpy; cs;s Fwpg;Gfspd;kPJ cq;fs; mtjhdj;ijr; nrYj;Jq;fs;.Njitahd jfty;fis cq;fs; gapw;rpg; Gj;jfj;jpy; Fwpj;Jf;nfhs;Sq;fs;.",
    "fonts": [
      "Kalaham"
    ],
    "sizes": [
      12.000008583068848
    ]
  },
  {
    "page_number": 2,
    "bbox": [
      108.36,
      292.09,
      220.05,
      303.09
    ],
    "text": "jha;g;ghYld; Nkyjpf",
    "fonts": [
      "Kalaham"
    ],
    "sizes": [
      11.000007629394531
    ]
  },
  {
    "page_number": 2,
    "bbox": [
      108.36,
      310.81,
      226.78,
      321.81
    ],
    "text": "czTfis toq;Fjy;",
    "fonts": [
      "Kalaham"
    ],
    "sizes": [
      11.000007629394531
    ]
  },
  {
    "page_number": 2,
    "bbox": [
      108.36,
      329.53,
      263.81,
      340.53
    ],
    "text": "- jputj; jd;ikahd czTfs;",
    "fonts": [
      "Kalaham"
    ],
    "sizes": [
      11.000007629394531
    ]
  },
  {
    "page_number": 2,
    "bbox": [
      108.36,
      348.25,
      254.04,
      359.25
    ],
    "text": "- Fiw jpz;kkhd czTfs;",
    "fonts": [
      "Kalaham"
    ],
    "sizes": [
      11.000007629394531
    ]
  },
  {
    "page_number": 2,
    "bbox": [
      108.36,
      366.97,
      203.63,
      377.97
    ],
    "text": "- jpz;k czTfs;",
    "fonts": [
      "Kalaham"
    ],
    "sizes": [
      11.000007629394531
    ]
  },
  {
    "page_number": 2,
    "bbox": [
      174.84,
      410.61,
      413.31,
      466.77
    ],
    "text": "ftdpf;f Ntz;baitftdpf;f Ntz;baitftdpf;f Ntz;baitftdpf;f Ntz;baitftdpf;f Ntz;baitjpdKk; xU Kiw Gspg;Gr; RitAs;s goq;fs;>tpyq;F czTfis toq;Fjy;. rPdp> cg;Gvd;gtw;iw cztpy; Nru;j;jyhfhJ.",
    "fonts": [
      "Kalaham"
    ],
    "sizes": [
      11.000007629394531
    ]
  },
  {
    "page_number": 2,
    "bbox": [
      336.48,
      317.89,
      482.75,
      369.21
    ],
    "text": "fpoq;F tiffs;> Kl;ilapd;kQ;rl; fU> fPiu tiffs;>,iwr;rp> kPd;> fUthL>kQ;rs; epwg; goq;fs;",
    "fonts": [
      "Kalaham"
    ],
    "sizes": [
      11.000007629394531
    ]
  },
  {
    "page_number": 2,
    "bbox": [
      278.64,
      264.13,
      469.05,
      318.33
    ],
    "text": "FOe;ijapd; Njitf;FVw;g toq;Fjy;jha;g;ghy;kl;Lk;6khjk;tiu",
    "fonts": [
      "Kalaham"
    ],
    "sizes": [
      11.000007629394531
    ]
  },
  {
    "page_number": 2,
    "bbox": [
      267.96,
      333.01,
      311.41,
      383.61
    ],
    "text": "6 khjk;Kjy;1 tUlk;tiu",
    "fonts": [
      "Kalaham"
    ],
    "sizes": [
      11.000007629394531
    ]
  },
  {
    "page_number": 2,
    "bbox": [
      334.68,
      501.84,
      483.11,
      529.53
    ],
    "text": "\u2022 rPdp> cg;G Mfpatw;iwf; Fiwe;jstpy; toq;Fjy;.",
    "fonts": [
      "Kalaham",
      "Symbol"
    ],
    "sizes": [
      11.000007629394531
    ]
  },
  {
    "page_number": 2,
    "bbox": [
      334.68,
      543.84,
      468.11,
      571.53
    ],
    "text": "\u2022 nraw;if czTfisj; jtpu;j;Jf;nfhs;sy;.",
    "fonts": [
      "Kalaham",
      "Symbol"
    ],
    "sizes": [
      11.000007629394531
    ]
  },
  {
    "page_number": 2,
    "bbox": [
      334.68,
      585.84,
      484.2,
      669.45
    ],
    "text": "\u2022nraw;if cztpy; cs;sRita+l;bfs;> epw%l;bfs;>ew;fhg;Gg; gjhu;j;jq;fs;Nghd;wit <uw; Gw;WNeha;>ePupopT Neha; vd;gtw;iwj;Njhw;Wtpf;fyhk;.",
    "fonts": [
      "Kalaham",
      "Symbol"
    ],
    "sizes": [
      11.000007629394531
    ]
  },
  {
    "page_number": 2,
    "bbox": [
      113.52,
      495.6,
      262.11,
      707.01
    ],
    "text": "\u2022rhjhuz czTfismwpKfg;gLj;jy;.\u2022thuj;jpw;F %d;W jlitgUg;G tif(mtiuapd)czTfis toq;Fjy;.\u2022mjpfsT rf;jpia toq;Fk;czTfis toq;Fjy;.\u2022jpdKk; kuf;fwp> gotiffs;Nghd;wtw;iwAk; NghjpasTngw;Wf;nfhs;sy;.\u2022toq;fg;gLk; cztpd;msT gps;isapd; cauk;>epiw> nraw;ghL> Mz; -ngz; ghy; NtWghLfSf;Fmikthf ,Uf;f Ntz;Lk;.",
    "fonts": [
      "Kalaham",
      "Symbol"
    ],
    "sizes": [
      11.000007629394531,
      12.000008583068848
    ]
  },
  {
    "page_number": 2,
    "bbox": [
      267.48,
      522.01,
      325.21,
      559.41
    ],
    "text": "gps;isfs; (1 - 10 taJ)",
    "fonts": [
      "Kalaham"
    ],
    "sizes": [
      11.000007629394531
    ]
  },
  {
    "page_number": 2,
    "bbox": [
      256.44,
      209.77,
      325.08,
      223.77
    ],
    "text": "Foe;ijfs;",
    "fonts": [
      "Kalaham"
    ],
    "sizes": [
      14.000009536743164
    ]
  },
  {
    "page_number": 2,
    "bbox": [
      198.3,
      182.31,
      395.44,
      194.67
    ],
    "text": "Foe;ijg; gUt Cl;lj; Njitfs;Foe;ijg; gUt Cl;lj; Njitfs;Foe;ijg; gUt Cl;lj; Njitfs;Foe;ijg; gUt Cl;lj; Njitfs;Foe;ijg; gUt Cl;lj; Njitfs;",
    "fonts": [
      "Kalaham"
    ],
    "sizes": [
      12.000008583068848
    ]
  },
  {
    "page_number": 2,
    "bbox": [
      198.9,
      475.95,
      393.53,
      488.31
    ],
    "text": "gps;isg; gUt Cl;lj; Njitfs;gps;isg; gUt Cl;lj; Njitfs;gps;isg; gUt Cl;lj; Njitfs;gps;isg; gUt Cl;lj; Njitfs;gps;isg; gUt Cl;lj; Njitfs;",
    "fonts": [
      "Kalaham"
    ],
    "sizes": [
      12.000008583068848
    ]
  },
  {
    "page_number": 3,
    "bbox": [
      287.76,
      716.12,
      487.64,
      738.45
    ],
    "text": ",ytr tpepNahfj;jpw;fhf109",
    "fonts": [
      "Kalaham",
      "Times-Roman"
    ],
    "sizes": [
      8.00001335144043,
      12.000008583068848
    ]
  },
  {
    "page_number": 3,
    "bbox": [
      167.94,
      410.55,
      375.76,
      422.91
    ],
    "text": "fl;bsikg; gUt Cl;lj; Njitfs;fl;bsikg; gUt Cl;lj; Njitfs;fl;bsikg; gUt Cl;lj; Njitfs;fl;bsikg; gUt Cl;lj; Njitfs;fl;bsikg; gUt Cl;lj; Njitfs;",
    "fonts": [
      "Kalaham"
    ],
    "sizes": [
      12.000008583068848
    ]
  },
  {
    "page_number": 3,
    "bbox": [
      114.48,
      179.52,
      295.2,
      403.17
    ],
    "text": "\u2022clypy; Gw> mf khw;wq;fs; gyeilngWfpd;w fhykhFk;. \u2022Gujk; mjpfKs;s czTfisAk;mjpfsT rf;jpia toq;Fk;fhNghitjNuw;W> ,ypg;gpl;L;mlq;fpa czTfisAk; toq;Fjy;. \u2022vd;G> jir tsu;r;rp eilngWtjhy;fdpAg;Gfs; mjpfKs;s czTfis toq;Fjy;. \u2022#oYf;Fj; Jyq;fy;fisf; fhl;Lk;,ay;G mjpfkhf ,Ug;gjdhy;Neha; vjpu;g;Gj; jd;ikiamjpfupg;gjw;F mjpfstpy; tpw;wkpd;cs;s czTfshd> kuf;fwp> fPiutiffis cztpy; Nrh;j;jy;.",
    "fonts": [
      "Kalaham",
      "Symbol"
    ],
    "sizes": [
      11.000007629394531
    ]
  },
  {
    "page_number": 3,
    "bbox": [
      142.62,
      133.35,
      373.24,
      145.71
    ],
    "text": "Kd;fl;bsikg; gUt Cl;lj; Njitfs;Kd;fl;bsikg; gUt Cl;lj; Njitfs;Kd;fl;bsikg; gUt Cl;lj; Njitfs;Kd;fl;bsikg; gUt Cl;lj; Njitfs;Kd;fl;bsikg; gUt Cl;lj; Njitfs;",
    "fonts": [
      "Kalaham"
    ],
    "sizes": [
      12.000008583068848
    ]
  },
  {
    "page_number": 3,
    "bbox": [
      185.34,
      153.51,
      424.1,
      165.87
    ],
    "text": "Kd;fl;bsikg; gUtj;jpdu;Kd;fl;bsikg; gUtj;jpdu;Kd;fl;bsikg; gUtj;jpdu;Kd;fl;bsikg; gUtj;jpdu;Kd;fl;bsikg; gUtj;jpdu; (10 - 14 taJ)",
    "fonts": [
      "Kalaham"
    ],
    "sizes": [
      11.000007629394531,
      12.000008583068848
    ]
  },
  {
    "page_number": 3,
    "bbox": [
      246.12,
      512.21,
      295.93,
      545.01
    ],
    "text": ";fl;bsikg;gUtj;jpdu;",
    "fonts": [
      "Kalaham"
    ],
    "sizes": [
      7.000004768371582,
      11.000007629394531
    ]
  },
  {
    "page_number": 3,
    "bbox": [
      191.04,
      426.85,
      447.48,
      463.89
    ],
    "text": "tpNrlkhf ,sk; ngz; gps;isfSf;Fj; NjitahdNghrizia toq;Fjy;. my;yhtpbd; gpw;fhyj;jpy;jha;ik miltjpy; rpf;fy;fs; Njhd;Wk;.",
    "fonts": [
      "Kalaham"
    ],
    "sizes": [
      11.000007629394531
    ]
  },
  {
    "page_number": 3,
    "bbox": [
      115.32,
      482.65,
      213.95,
      558.69
    ],
    "text": "tpw;wkpd;fs;>fdpAg;Gfs;>maBd; cs;sczTfismjpfstpy; cztpy;Nrh;j;Jf;nfhs;sy;.",
    "fonts": [
      "Kalaham"
    ],
    "sizes": [
      11.000007629394531
    ]
  },
  {
    "page_number": 3,
    "bbox": [
      331.32,
      485.89,
      474.49,
      550.89
    ],
    "text": "vg;nghOJk; Nghrizkpf;fczTfis toq;Fjy;mt;thwpy;yhtpbd;ke;j Nghriz> Fiwghl;LNeha;fs; Njhd;Wk;.",
    "fonts": [
      "Kalaham"
    ],
    "sizes": [
      11.000007629394531
    ]
  },
  {
    "page_number": 3,
    "bbox": [
      271.32,
      574.57,
      326.03,
      585.57
    ],
    "text": "tsu;e;Njhu;",
    "fonts": [
      "Kalaham"
    ],
    "sizes": [
      11.000007629394531
    ]
  },
  {
    "page_number": 3,
    "bbox": [
      119.76,
      609.13,
      234.81,
      700.17
    ],
    "text": "Fiwe;jsthdfNyhupg;ngW khdNkNjitg;gLtjhy;cl;nfhs;Sk; cztpd;msitf; Fiwg;gjd;%yk; cly; epiwiag;NgZjy;",
    "fonts": [
      "Kalaham"
    ],
    "sizes": [
      11.000007629394531
    ]
  },
  {
    "page_number": 3,
    "bbox": [
      278.52,
      599.52,
      475.58,
      707.49
    ],
    "text": "\u2022rf;jpia toq;Fk; czTfisf;Fiwe;jstpy; cl;nfhs;sy;.\u2022cztpy; ,iwr;rp> Kl;il> gl;lu;> rP];vd;gtw;iwf;s Fiwthfr; Nrh;j;Jf;nfhs;sy;.\u2022kuf;fwp> goq;fs;> fPiu tiffs;Mfpatw;iwj; Njitahd mstpy;cs;nsLj;jy;.",
    "fonts": [
      "Kalaham",
      "Times-Roman"
    ],
    "sizes": [
      10.000007629394531,
      11.000007629394531
    ]
  },
  {
    "page_number": 3,
    "bbox": [
      322.32,
      179.28,
      481.59,
      387.93
    ],
    "text": "\u2022jhdpa czTfis jtpLePf;fhJ toq;Fjy;.\u2022tpyq;FzTfis jpdKk; xUNtisahtJ toq;Fjy;.\u2022tpyq;FzTfis cl;nfhs;shjtu;fSf;F Nrhah>gUg;G tifahd (mtiuapd)khw;W czTfis toq;Fjy;.\u2022thuk; xU Kiw Gspg;Gj;jd;ikahd goq;fisr;Nrh;j;Jf;nfhs;sy;. ,itvd;Gf;fyq;fs;> FUjp vd;gtw;wpd; tpUj;jpf;F mtrpakhdit MFk;.",
    "fonts": [
      "Kalaham",
      "Symbol"
    ],
    "sizes": [
      11.000007629394531
    ]
  },
  {
    "page_number": 4,
    "bbox": [
      108.48,
      716.72,
      305.76,
      737.01
    ],
    "text": ",ytr tpepNahfj;jpw;fhf110",
    "fonts": [
      "Kalaham",
      "Times-Roman"
    ],
    "sizes": [
      8.00001335144043,
      12.000008583068848
    ]
  },
  {
    "page_number": 4,
    "bbox": [
      181.68,
      405.24,
      476.64,
      511.29
    ],
    "text": "\u2022 gapw;rpf; fhyq;fspd;NghJ mjpfsT fNyhup rf;jptpuakhtjhy; rf;jpia toq;Fk; czTfis mjpfsTtoq;f Ntz;Lk;. \u2022 Gujk; mjpfsTs;s czTfis mjpfk; cl;nfhs;sNtz;Lk;. \u2022 tpw;wkpd;> fdpAg;G mlq;fpa czTfs;> kQ;rs; - nrk;kQ;rs;epwKs;s goq;fs;> kuf;fwp> fPiutiffs; cs;sczTfis toq;f Ntz;Lk;.",
    "fonts": [
      "Kalaham",
      "Symbol"
    ],
    "sizes": [
      11.000007629394531
    ]
  },
  {
    "page_number": 4,
    "bbox": [
      112.44,
      153.01,
      160.41,
      177.21
    ],
    "text": "fu;g;gpzpj;jha;khu;",
    "fonts": [
      "Kalaham"
    ],
    "sizes": [
      11.000007629394531
    ]
  },
  {
    "page_number": 4,
    "bbox": [
      114.96,
      254.28,
      483.12,
      400.77
    ],
    "text": "ghY}l;Lk;jha;khu;fs;\u2022Gujk;> rf;jp toq;Fk; czT> tpw;wkpd;fs;> fdpAg;Gfs;cs;s czTfisr; Nrh;j;Jf;nfhs;s Ntz;Lk;.\u2022fu;g;g fhyj;jpy; ngw;Wf; nfhz;l cztpYk; ghu;f;fmjpfsT NghrizAs;s czTfis cl;nfhs;sNtz;Lk;.\u2022ehnshd;Wf;F 850 ml jha;g;ghy; cw;gj;jpahf;fg;gLtjhy;jha;f;F mjpfstpy; Nghrizkpf;f czTfisf;nfhLj;jy; Ntz;Lk;.\u2022Foe;ijf;F xU tUl fhyj;jpw;NfDk; jha;g;ghy; toq;fNtz;Lk;. Mjyhy;> Njitahd Nghrizia toq;fNtz;Lk;.",
    "fonts": [
      "Kalaham",
      "Symbol",
      "Times-Roman"
    ],
    "sizes": [
      11.000007629394531
    ]
  },
  {
    "page_number": 4,
    "bbox": [
      115.2,
      408.25,
      173.65,
      432.45
    ],
    "text": "tpisahl;LtPuu;fs;",
    "fonts": [
      "Kalaham"
    ],
    "sizes": [
      11.000007629394531
    ]
  },
  {
    "page_number": 4,
    "bbox": [
      188.4,
      520.8,
      484.16,
      560.85
    ],
    "text": "\u2022ehu;j;jd;ikAs;s czTfisr; Nrh;j;Jf;nfhs;s Ntz;Lk;.\u2022rPdp> ,dpg;Gj; jd;ikahd czTfisf; Fiwj;Jf;nfhs;s Ntz;Lk;.",
    "fonts": [
      "Kalaham",
      "Symbol"
    ],
    "sizes": [
      11.000007629394531
    ]
  },
  {
    "page_number": 4,
    "bbox": [
      113.52,
      527.89,
      178.8,
      552.09
    ],
    "text": "ePupopT Neha;cs;stu;fs;",
    "fonts": [
      "Kalaham"
    ],
    "sizes": [
      11.000007629394531
    ]
  },
  {
    "page_number": 4,
    "bbox": [
      188.52,
      570.84,
      479.87,
      703.29
    ],
    "text": ";\u2022,iwr;rp> Kl;il> vz;nza;j; jd;ikahd czTfisf;Fiwj;Jf;nfhs;sy;.\u2022ehu;j; jd;ikahd czit> ngw;Wf;nfhs;sy;.\u2022cly; epiwiaf; Fiwj;Jf;nfhs;Sjy;.\u2022cg;G> rPdp> Mfpatw;iw cztpy; Njitahd mstpy;khj;jpuk; Nrh;j;Jf;nfhs;sy;.rhjhuz re;ju;g;gq;fistpl Neha; cs;s epiyikfspy;NehahsUf;F Vw;g czitg; ngw;Wf;nfhs;Sk;Nfhyj;ij khw;wpaikf;f Ntz;Lk;. itj;jpaupd;MNyhridiag; ngw;Wf;nfhs;Sjy; Kf;fpakhdjhFk;).",
    "fonts": [
      "Kalaham",
      "Symbol"
    ],
    "sizes": [
      11.000007629394531
    ]
  },
  {
    "page_number": 4,
    "bbox": [
      112.2,
      571.57,
      181.18,
      635.37
    ],
    "text": ",ja Neha;>cau;FUjpaKf;fk;nfhz;lNehahspfs;",
    "fonts": [
      "Kalaham"
    ],
    "sizes": [
      11.000007629394531
    ]
  },
  {
    "page_number": 4,
    "bbox": [
      108.3,
      133.35,
      372.63,
      145.71
    ],
    "text": "tho;f;ifj; NjitfSf;Nfw;g Cl;l NtWghLtho;f;ifj; NjitfSf;Nfw;g Cl;l NtWghLtho;f;ifj; NjitfSf;Nfw;g Cl;l NtWghLtho;f;ifj; NjitfSf;Nfw;g Cl;l NtWghLtho;f;ifj; NjitfSf;Nfw;g Cl;l NtWghL",
    "fonts": [
      "Kalaham"
    ],
    "sizes": [
      12.000008583068848
    ]
  },
  {
    "page_number": 4,
    "bbox": [
      191.04,
      150.6,
      467.97,
      244.29
    ],
    "text": "\u2022rf;jpia toq;Fk; czTfs;> Gujk;> tpw;wkpd;fs;>fdpAg;Gfs; mlq;fpa czTfis mjpfstpy;cl;nfhs;sy;.\u2022Foe;ijapd; tsu;r;rpiaAk; jhapd; NjitfisAk;fUj;jpw;nfhs;Sjy;.\u2022Nkw;Fwpg;gpl;l mk;rq;fs; jha;g; ghy; toq;Fk; fhyj;jpy;mbg;gilahf mikfpwJ.",
    "fonts": [
      "Kalaham",
      "Symbol"
    ],
    "sizes": [
      11.000007629394531
    ]
  },
  {
    "page_number": 5,
    "bbox": [
      287.76,
      716.12,
      487.64,
      738.45
    ],
    "text": ",ytr tpepNahfj;jpw;fhf111",
    "fonts": [
      "Kalaham",
      "Times-Roman"
    ],
    "sizes": [
      8.00001335144043,
      12.000008583068848
    ]
  },
  {
    "page_number": 5,
    "bbox": [
      108.48,
      180.69,
      486.48,
      221.49
    ],
    "text": ",yq;if gy;ypd> gy kj kf;fs; thOk; ehlhFk;. cl;nfhs;Sk;czT tiffs;> ngw;Wf;nfhs;Sk; Kiw> gof;ftof;fq;fs; xt;nthU,dj;jpw;Fk; Vw;g NtWgl;Lf; fhzg;gLfpd;wd.",
    "fonts": [
      "Kalaham"
    ],
    "sizes": [
      12.000008583068848
    ]
  },
  {
    "page_number": 5,
    "bbox": [
      126.3,
      238.11,
      206.94,
      250.47
    ],
    "text": "nraw;ghL 8.2nraw;ghL 8.2nraw;ghL 8.2nraw;ghL 8.2nraw;ghL 8.2",
    "fonts": [
      "Kalaham"
    ],
    "sizes": [
      12.000008583068848
    ]
  },
  {
    "page_number": 5,
    "bbox": [
      126.48,
      258.69,
      479.73,
      299.49
    ],
    "text": "NtWgl;l ehl;ltu;fspd; czTg; gof;fq;fs; rikay; Kiw vd;gdgw;wpf; fz;lwpe;J mtw;wpd; Nghriz njhlu;ghf Mf;fG+u;tkhdtpku;rdq;fis Kd;itAq;fs;.",
    "fonts": [
      "Kalaham"
    ],
    "sizes": [
      12.000008583068848
    ]
  },
  {
    "page_number": 5,
    "bbox": [
      108.48,
      316.29,
      486.41,
      342.69
    ],
    "text": "ePq;fs; mwpf;ifg;gLj;jpa jfty;fspy; gpd;tUk; tplaq;fs;mlq;fpAs;sdth vdg; ghUq;fs;.",
    "fonts": [
      "Kalaham"
    ],
    "sizes": [
      12.000008583068848
    ]
  },
  {
    "page_number": 5,
    "bbox": [
      108.48,
      633.09,
      486.47,
      688.29
    ],
    "text": "Mjpfhyk; Kjy; ek;ehl;L kf;fs; ghuk;gupa czTfiscs;nsLg;gjpy; ftdQ; nrYj;jp tUfpd;wdu;. ,e;j tifapy; cztpd;Nghrizg; ngWkhdk; Fiwahky; czit cyu;j;jy;> rikj;jy;>Gifaply; Nghd;w Kiwfisf; ifahz;L te;Js;sdu;.",
    "fonts": [
      "Kalaham"
    ],
    "sizes": [
      12.000008583068848
    ]
  },
  {
    "page_number": 5,
    "bbox": [
      118.92,
      134.68,
      399.86,
      168.68
    ],
    "text": "Nghriz njhlu;ghd gy;NtW nfhs;iffSk;Nghriz njhlu;ghd gy;NtW nfhs;iffSk;Nghriz njhlu;ghd gy;NtW nfhs;iffSk;Nghriz njhlu;ghd gy;NtW nfhs;iffSk;Nghriz njhlu;ghd gy;NtW nfhs;iffSk; ek;gpf;iffSk ek;gpf;iffSk ek;gpf;iffSk ek;gpf;iffSk ek;gpf;iffSk",
    "fonts": [
      "Kalyani"
    ],
    "sizes": [
      16.000011444091797
    ]
  },
  {
    "page_number": 5,
    "bbox": [
      247.08,
      455.73,
      355.8,
      496.53
    ],
    "text": "cs;ehl;L ghuk;gupaczTfs; / fyhrhuczTfs;",
    "fonts": [
      "Kalaham",
      "Times-Roman"
    ],
    "sizes": [
      12.000008583068848
    ]
  },
  {
    "page_number": 5,
    "bbox": [
      370.32,
      387.85,
      421.18,
      398.85
    ],
    "text": "tl;byg;gk;",
    "fonts": [
      "Kalaham"
    ],
    "sizes": [
      11.000007629394531
    ]
  },
  {
    "page_number": 5,
    "bbox": [
      244.68,
      366.73,
      342.08,
      377.73
    ],
    "text": "rh;f;fiug; nghq;fy;",
    "fonts": [
      "Kalaham"
    ],
    "sizes": [
      11.000007629394531
    ]
  },
  {
    "page_number": 5,
    "bbox": [
      234.48,
      566.89,
      285.47,
      591.09
    ],
    "text": "fPiug;gpl;Lkzpg;gpl;L",
    "fonts": [
      "Kalaham"
    ],
    "sizes": [
      11.000007629394531
    ]
  },
  {
    "page_number": 5,
    "bbox": [
      367.2,
      567.49,
      421.91,
      591.69
    ],
    "text": "nghuptpshq;fha;",
    "fonts": [
      "Kalaham"
    ],
    "sizes": [
      11.000007629394531
    ]
  },
  {
    "page_number": 5,
    "bbox": [
      162.0,
      405.85,
      204.0,
      416.85
    ],
    "text": "gphpahzp",
    "fonts": [
      "Kalaham"
    ],
    "sizes": [
      11.000007629394531
    ]
  },
  {
    "page_number": 5,
    "bbox": [
      123.72,
      462.25,
      184.43,
      473.25
    ],
    "text": ",iyf;fQ;rp",
    "fonts": [
      "Kalaham"
    ],
    "sizes": [
      11.000007629394531
    ]
  },
  {
    "page_number": 5,
    "bbox": [
      130.32,
      535.09,
      177.58,
      546.09
    ],
    "text": "xbaw;$o;",
    "fonts": [
      "Kalaham"
    ],
    "sizes": [
      11.000007629394531
    ]
  },
  {
    "page_number": 5,
    "bbox": [
      409.92,
      468.49,
      445.2,
      479.49
    ],
    "text": "rhk;ghu;",
    "fonts": [
      "Kalaham"
    ],
    "sizes": [
      11.000007629394531
    ]
  },
  {
    "page_number": 6,
    "bbox": [
      108.48,
      716.72,
      305.76,
      737.01
    ],
    "text": ",ytr tpepNahfj;jpw;fhf112",
    "fonts": [
      "Kalaham",
      "Times-Roman"
    ],
    "sizes": [
      8.00001335144043,
      12.000008583068848
    ]
  },
  {
    "page_number": 6,
    "bbox": [
      108.48,
      133.53,
      486.49,
      174.33
    ],
    "text": "vkf;nfd;W Nghrizkpf;f Njrpa czT tiffs; gyfhzg;gl;lhYk; ehk; mtw;iw kwe;J gy;NtW nraw;if czT tiffiscl;nfhs;sg; gofpAs;Nshk;.",
    "fonts": [
      "Kalaham"
    ],
    "sizes": [
      12.000008583068848
    ]
  },
  {
    "page_number": 6,
    "bbox": [
      108.48,
      191.13,
      486.45,
      246.33
    ],
    "text": "nghJthf> gy;NtW Clfq;fspD}lhfTk; xypgug;gg;gLfpd;wtpsk;guq;fspd; fhuzkhf clYf;Fj; jPq;if Vw;gLj;Jk; nraw;ifczTfspd;kPJ ehl;lk; nfhz;L Nghrizkpf;f czTfis xJf;fpitf;fpd;Nwhk;.",
    "fonts": [
      "Kalaham"
    ],
    "sizes": [
      12.000008583068848
    ]
  },
  {
    "page_number": 6,
    "bbox": [
      108.48,
      263.13,
      486.66,
      361.53
    ],
    "text": "vdpDk;> ghlrhiyf; fy;tpiag; ngWk; ePq;fs;> ,t;tifahdnraw;if czTfspd;kPJ ehl;lk; nfhs;shky; rpwe;j jukhdczTfisj; njupT nra;Jf; nfhs;Sk; Mw;wiy tsh;j;Jf;nfhs;sNtz;Lk;. vg;nghOJk; cq;fs; MNuhf;fpaj;jpd;kPJ mf;fiwAs;stuhfePq;fs; ,Uf;f Ntz;Lk;. ePq;fs; rupahd czitj; njupTnra;Jnfhs;tJld; cq;fs; ez;gu;fSf;Fr; rupahd ghijiaf; fhl;LtJk;cq;fs; flikahFk;.",
    "fonts": [
      "Kalaham"
    ],
    "sizes": [
      12.000008583068848
    ]
  },
  {
    "page_number": 6,
    "bbox": [
      108.3,
      478.95,
      357.62,
      491.31
    ],
    "text": "Cl;lk; njhlu;ghff; ftdpf;f Ntz;baitCl;lk; njhlu;ghff; ftdpf;f Ntz;baitCl;lk; njhlu;ghff; ftdpf;f Ntz;baitCl;lk; njhlu;ghff; ftdpf;f Ntz;baitCl;lk; njhlu;ghff; ftdpf;f Ntz;bait",
    "fonts": [
      "Kalaham"
    ],
    "sizes": [
      12.000008583068848
    ]
  },
  {
    "page_number": 6,
    "bbox": [
      108.48,
      507.93,
      486.49,
      563.13
    ],
    "text": "vkJ Cl;lj; Njitfis epiwNtw;w tpahghu epiyaq;fspy;czTg; gz;lq;fis tpiy nfhLj;J thq;fg; gof;fg;gl;Ls;Nshk;.ngUk;ghYk; tpahghu tpsk;guq;fspD}lhfg; nghJkf;fspy; jtwhdkdg;ghq;Ffs; Vw;gLj;jg;gLfpd;wd.",
    "fonts": [
      "Kalaham"
    ],
    "sizes": [
      12.000008583068848
    ]
  },
  {
    "page_number": 6,
    "bbox": [
      108.48,
      579.93,
      486.72,
      692.73
    ],
    "text": ",d;W tu;j;jf epiyaq;fspy; tpw;fg;gLk; cldb czTfs;>RitA+l;b Nru;f;fg;gl;l czTfs;> Cl;lr;rj;Jf; Fiwe;j czTfs;vd;gdtw;wpd; ftu;r;rpfukhd tpsk;guq;fshy; mtw;iw thq;Ftjpy; kf;fs;mjpf Mu;tk; fhl;Lfpwhu;fs;. Mdhy;> mit cupa gz;G juj;ijf;nfhz;litay;y. vdpDk;> ,aw;if czTfs; cau;Nghrizg; ngWkhdk;nfhz;litahfTk; kypthditahfTk;> NehapypUe;J ghJfhg;G ngwf;$badthfTk; cs;sd. vdNt> kf;fs; jukhd czit njupT nra;tjpy;mjpf tpopg;Gld; nraw;gl Ntz;Lk;.",
    "fonts": [
      "Kalaham"
    ],
    "sizes": [
      12.000008583068848
    ]
  },
  {
    "page_number": 6,
    "bbox": [
      129.66,
      386.07,
      196.02,
      398.43
    ],
    "text": "xg;gil 8.1xg;gil 8.1xg;gil 8.1xg;gil 8.1xg;gil 8.1",
    "fonts": [
      "Kalaham"
    ],
    "sizes": [
      12.000008583068848
    ]
  },
  {
    "page_number": 6,
    "bbox": [
      129.84,
      406.65,
      475.63,
      447.45
    ],
    "text": "cq;fs; ez;gu;fisr; nraw;if czTg; gof;fj;jpypUe;J tpLtpj;Jf;nfhs;sg; nghUj;jkhd mwpTiu toq;ff;$ba Rtu;g;gj;jpupif xd;iwj;jahupAq;fs;. ,jid mjpgupd; mDkjpAld; fhl;rpg;gLj;Jq;fs;.",
    "fonts": [
      "Kalaham"
    ],
    "sizes": [
      12.000008583068848
    ]
  }
]