[
  {
    "page_number": 0,
    "bbox": [
      294.48,
      720.93,
      486.47,
      740.36
    ],
    "text": "1,ytr ghlE}y; tpepNahfj;jpw;fhf",
    "fonts": [
      "Kalaham",
      "Times-Roman"
    ],
    "sizes": [
      9.000006675720215,
      12.000008583068848
    ]
  },
  {
    "page_number": 0,
    "bbox": [
      125.51,
      492.61,
      469.5,
      510.12
    ],
    "text": "6.1 tho;thjhuj; njhopnyhd;iwj; njupT nra;jy; 6.1 tho;thjhuj; njhopnyhd;iwj; njupT nra;jy; 6.1 tho;thjhuj; njhopnyhd;iwj; njupT nra;jy; 6.1 tho;thjhuj; njhopnyhd;iwj; njupT nra;jy; 6.1 tho;thjhuj; njhopnyhd;iwj; njupT nra;jy;",
    "fonts": [
      "Kalyani"
    ],
    "sizes": [
      17.000011444091797
    ]
  },
  {
    "page_number": 0,
    "bbox": [
      108.48,
      527.73,
      486.57,
      683.73
    ],
    "text": "njhopy; vd;gJ ntWkNd jdpg;gl;lnjhU nraw;ghL kl;Lky;y.khwhfg; gad; kpf;f nraw;ghl;by; <Lgly; %yk; cw;gj;jpr; nraw;ghLfspd;gq;fhspahfp ehl;bd; mgptpUj;jpf;F NeubahfNth my;yJ kiwKfkhfNthgq;fspg;Gr; nra;tjhFk;. ePq;fs; vl;lhk; juj;jpy; NtiyAyF gw;wpf;fw;w tplaq;fis epidT $Wq;fs;. murJiwapy;> jdpahu; Jiwapy;my;yJ Ra Kaw;rpapy; cs;s vj;njhopYf;fhapDk; jdpg;gl;l ngWkjpkl;Lkd;wp r%fg; ngWkjpAk; cz;L. mJ kl;Lkd;wp tWik kw;Wk;r%f Kuz;ghLfis ,y;yhky; nra;tjw;Ff;$l ,J fhuzkhfmikfpd;wJ. vdNt njhopnyhd;iwj; njupTnra;Ak; NghJ kpf MokhdmwpTlDk;> ftdj;JlDk; nraw;gl Ntz;Lk;.",
    "fonts": [
      "Kalaham"
    ],
    "sizes": [
      12.000008583068848
    ]
  },
  {
    "page_number": 0,
    "bbox": [
      123.96,
      184.85,
      473.45,
      469.77
    ],
    "text": "r%f mq;fj;jtu;fspd; ed;ik fUjp Nkw;nfhs;sg;gLfpd;w rfykdpj eltbf;iffSk; NtiyAyfpw;Fs; cs;thq;fg;gLfpd;wd.rkfhyj;J tpQ;Qhd njhopDl;gj;jpwd;fspy; Vw;gl;Ls;sKd;Ndw;wj;Jld; NtiyAyFk; tpiuthf tpahgpj;Jf;fhzg;gLfpd;wJ. ehSf;F ehs; tpahgpj;Jr; nry;fpd;w ,e;jNtiyAyfpDs; cq;fSf;nfd;W vjpu;fhyj;jpy; Xuplk;xJf;fg;gl;Ls;sJ. ,t;tplj;jpid kpfTk; gaDilajhf;fpf;nfhs;tjw;F cq;fSila tpUg;gk;> Nehf;fk; vd;gd NghyNtghlrhiy kw;Wk; Rw;Wr; #oypypUe;J ePq;fs; ngw;Wf; nfhz;lMw;wy;fs; vd;gdTk; gq;fspg;Gr; nra;fpd;wd. ~~VNjh xU njhopy;||vd;w epiyad;wp cq;fsJ Mw;wy;fs;> Mu;tk; vd;gtw;Wf;Fg;nghUj;jkhd njhopy; my;yJ Ranjhopy; xd;wpy; <Lgl Ntz;Lk;.mjw;Fj; Njitahd mbg;gilj; Nju;r;rpfisg; G+uzg;gLj;jpf;nfhs;tJ mtrpakhFk;. ,jw;F njhopYyif Ma;Tf;Fl;gLj;jpnray;jpwDld; $ba gz;G rhu; Nritnahd;iw ehl;bw;F toq;fNtz;Lk;. vdNt vjpu;fhyj;jpy; njhopy; xd;wpy; gpuNtrpg;gjw;Fj;Njitahd gpd;dzpiag; ngw;Wf; nfhLg;gNj ,g;ghlj;jpd;Nehf;fkhFk;.",
    "fonts": [
      "Kalaham"
    ],
    "sizes": [
      13.000009536743164
    ]
  },
  {
    "page_number": 0,
    "bbox": [
      95.28,
      135.0,
      468.46,
      166.0
    ],
    "text": "Ntiy cyFf;F Maj;jkhNthk;Ntiy cyFf;F Maj;jkhNthk;Ntiy cyFf;F Maj;jkhNthk;Ntiy cyFf;F Maj;jkhNthk;Ntiy cyFf;F Maj;jkhNthk;6",
    "fonts": [
      "Alankaram",
      "FMEmanee"
    ],
    "sizes": [
      16.000011444091797,
      18.00001335144043,
      31.000022888183594
    ]
  },
  {
    "page_number": 1,
    "bbox": [
      108.48,
      720.93,
      300.48,
      740.36
    ],
    "text": "2,ytr ghlE}y; tpepNahfj;jpw;fhf",
    "fonts": [
      "Kalaham",
      "Times-Roman"
    ],
    "sizes": [
      9.000006675720215,
      12.000008583068848
    ]
  },
  {
    "page_number": 1,
    "bbox": [
      108.48,
      310.53,
      486.47,
      514.53
    ],
    "text": "ve;j xU njhopiyAk; ~~cau;e;jJ> jho;e;jJ|| vd tFj;J Nehf;fKbahJ. vdpDk; ,t;tplaj;jpy; kpf Kf;fpakhtJ jkf;Fg; nghUj;jkhdrpwe;j xU njhopiyj; njupT nra;tJk;> njupT nra;j njhopy; gw;wpRa jpUg;jpAld; kw;Wk; tpidj;jpwDld; mj;njhopYld; rk;ge;jg;gl;lnraw;ghLfspy; <LgLtJkhFk;.md;W ky;thid kfh tpj;jpahya 9 Mk;ju khztu;fSf;fhfxOq;F nra;ag;gl;l ~~tho;f;ifj; Nju;r;rp|| jpdkhFk;. ,e;epfo;tpd;NghJ~~tho;thjhuj; njhopnyhd;iwj; Nju;e;njLg;Nghk;|| vDk; jiyg;gpd;fPo;ciu epfo;j;jntd tpNrl Ngr;rhsu; xUtu; miof;fg;gl;bUe;jhu;. gy;Y}lfvwpap xd;iwg; (Multi Media Projector) gad;gLj;jpathW Muk;gpf;fg;gl;lmtupd; ciu khztu;fspd; ftdj;ij <u;j;jjhf tpsq;fpaJ.fPNo fhzg;gLtJ epfo;tpd;NghJ jpiuapy; fhl;rpg;gLj;jg;gl;lglk; MFk;.",
    "fonts": [
      "Kalaham",
      "Times-Roman"
    ],
    "sizes": [
      12.000008583068848
    ]
  },
  {
    "page_number": 1,
    "bbox": [
      263.88,
      193.32,
      328.31,
      239.72
    ],
    "text": "rfynjhopy;fSk;r%f tpUj;jpf;Ff;fhuzkhfmikfpd;wd",
    "fonts": [
      "Kalaham"
    ],
    "sizes": [
      8.000005722045898
    ]
  },
  {
    "page_number": 1,
    "bbox": [
      191.4,
      700.09,
      403.68,
      711.09
    ],
    "text": ",isQu;fis NtiyAyfpw;F topfhl;ly;",
    "fonts": [
      "Kalaham"
    ],
    "sizes": [
      11.000007629394531
    ]
  },
  {
    "page_number": 1,
    "bbox": [
      224.88,
      536.61,
      270.59,
      548.61
    ],
    "text": "jPu;khdk;",
    "fonts": [
      "Kalaham"
    ],
    "sizes": [
      12.000008583068848
    ]
  },
  {
    "page_number": 1,
    "bbox": [
      171.12,
      572.61,
      293.77,
      595.41
    ],
    "text": "Mw;wy;fs;kdg;ghq;Ffs;",
    "fonts": [
      "Kalaham"
    ],
    "sizes": [
      12.000008583068848
    ]
  },
  {
    "page_number": 1,
    "bbox": [
      281.64,
      526.53,
      424.59,
      556.41
    ],
    "text": "Mirfs;vjpu;ghu;g;Gfs;kdg;ghq;Ffs;",
    "fonts": [
      "Kalaham"
    ],
    "sizes": [
      12.000008583068848
    ]
  },
  {
    "page_number": 1,
    "bbox": [
      256.32,
      602.25,
      299.03,
      628.65
    ],
    "text": "<LghLnghWg;G",
    "fonts": [
      "Kalaham"
    ],
    "sizes": [
      12.000008583068848
    ]
  },
  {
    "page_number": 1,
    "bbox": [
      336.48,
      584.25,
      398.87,
      596.25
    ],
    "text": "NtiyAyF",
    "fonts": [
      "Kalaham"
    ],
    "sizes": [
      12.000008583068848
    ]
  },
  {
    "page_number": 1,
    "bbox": [
      358.8,
      652.41,
      427.67,
      693.21
    ],
    "text": "thd;ikj;Jttuk;Gvy;iy",
    "fonts": [
      "Kalaham"
    ],
    "sizes": [
      12.000008583068848
    ]
  },
  {
    "page_number": 1,
    "bbox": [
      226.32,
      659.97,
      266.75,
      686.37
    ],
    "text": "Nkyjpffy;tp",
    "fonts": [
      "Kalaham"
    ],
    "sizes": [
      12.000008583068848
    ]
  },
  {
    "page_number": 2,
    "bbox": [
      294.48,
      720.93,
      486.47,
      740.36
    ],
    "text": "3,ytr ghlE}y; tpepNahfj;jpw;fhf",
    "fonts": [
      "Kalaham",
      "Times-Roman"
    ],
    "sizes": [
      9.000006675720215,
      12.000008583068848
    ]
  },
  {
    "page_number": 2,
    "bbox": [
      108.48,
      134.61,
      486.44,
      194.61
    ],
    "text": ",g;glj;jpd; %yk; Kd;itf;fg;gLk; fUj;Jf;fs; gw;wpg; Ngr;rhsu;>khztu;fspd; ftdj;jpw;Ff; nfhz;L te;jhu;. gy khztu;fs; jkJfUj;Jf;fisj; njuptpj;jdu;. ,f;fUj;Jf;fSs; kpfr; rupahd tpilahfVw;Wf;nfhs;sg;gl;lJ rkPu vd;w khztdpd; gpd;tUk; gjpyhFk;.",
    "fonts": [
      "Kalaham"
    ],
    "sizes": [
      12.000008583068848
    ]
  },
  {
    "page_number": 2,
    "bbox": [
      108.48,
      206.61,
      486.47,
      314.61
    ],
    "text": "~~tho;f;if vDk; ePz;l gazj;jpy; njhopy; xd;iwj; Nju;e;njLg;gJxU Kf;fpa rf;jpahFk;. ehk; ,r;re;ju;g;gj;jpy;> ve;jj; jpirapy;> ve;jKiwapy; gazpf;f Ntz;Lk; vd;w topfhl;ly;fs; fhl;rpg;glj;jpy;Fwpg;gplg;gl;Ls;sd. ehk; ,r;rf;jpia mila Kd;du; Rakjpg;gPl;bd;%yk; vkJ tpUg;gq;fs;> jpwikfs; kw;Wk; vjpu;ghu;g;Gf;fs; vd;gtw;iw,dq;fhz Ntz;Lk;. ,NjNghd;W njhopy; Ma;T kw;Wk; kdg;ghq;Ftsu;r;rpia Nkk;gLj;Jjy; vd;gd ,q;F Kf;fpakhFk;.",
    "fonts": [
      "Kalaham"
    ],
    "sizes": [
      12.000008583068848
    ]
  },
  {
    "page_number": 2,
    "bbox": [
      108.48,
      326.61,
      486.48,
      370.53
    ],
    "text": "NkYk; ehk; Nkw;Fwpg;gpl;l $w;wpy; cs;s NtiyAyFld;njhlu;Gila gy;NtWgl;l fUj;Jf;fspd; gf;fk; ekJ ftdj;ijr;nrYj;JNthk;.",
    "fonts": [
      "Kalaham"
    ],
    "sizes": [
      12.000008583068848
    ]
  },
  {
    "page_number": 2,
    "bbox": [
      254.61,
      390.01,
      340.81,
      407.52
    ],
    "text": "Ra kjpg;gPLRa kjpg;gPLRa kjpg;gPLRa kjpg;gPLRa kjpg;gPL",
    "fonts": [
      "Kalyani"
    ],
    "sizes": [
      14.000009536743164,
      17.000011444091797
    ]
  },
  {
    "page_number": 2,
    "bbox": [
      108.48,
      418.53,
      486.42,
      446.61
    ],
    "text": "mjhtJ jd;idg; gw;wpa Rakjpg;gPL xd;wpd; %yk; jdJ Mw;wy;fs;><LghLfs;> vjpu;ghu;g;Gf;fs; vd;gdtw;iw ,dq;fhz;gjhFk;.",
    "fonts": [
      "Kalaham"
    ],
    "sizes": [
      12.000008583068848
    ]
  },
  {
    "page_number": 2,
    "bbox": [
      108.48,
      489.57,
      486.45,
      709.53
    ],
    "text": "cq;fs; vjpu;fhyj; njhopy;vt;thW mika Ntz;Lk; vd;gijj;jPu;khdpf;f Ntz;batu;fs; ePq;fNsahtu;.tho;f;ifj; Nju;r;rp ghlj;jpy; Kjyhk;myfpy; ePq;fs; fw;w tplaq;fisr; rpwpJepidT+l;bg; ghUq;fs;. cq;fsplk;gy;NtWgl;l jpwik fSk;> Mw;wy;fSk;fhzg;gLfpd;wd. mj;jpwikfs;Mw;wy;fis kpfr; rpwg;ghf cq;fshy;,dq;fz;L nfhs;s KbAk;. ,jw;fhfg;ngw;Nwhu;> Mrpupau;fs; Nghd;w%j;NjhupdJk;> VidNahupdJk; xj;Jiog;igg; ngw;Wf; nfhs;syhk;. ,NjNghd;W rkfhy ghlrhiyg; ghltpjhdj;jpYk; ,jw;fhd trjpfs; nra;J",
    "fonts": [
      "Kalaham"
    ],
    "sizes": [
      12.000008583068848
    ]
  },
  {
    "page_number": 2,
    "bbox": [
      427.8,
      548.4,
      466.07,
      566.0
    ],
    "text": "vdJMw;wy;fs;",
    "fonts": [
      "Kalaham"
    ],
    "sizes": [
      8.000005722045898
    ]
  },
  {
    "page_number": 2,
    "bbox": [
      347.04,
      543.96,
      371.04,
      561.56
    ],
    "text": "vdJ<LghL",
    "fonts": [
      "Kalaham"
    ],
    "sizes": [
      8.000005722045898
    ]
  },
  {
    "page_number": 2,
    "bbox": [
      371.16,
      515.52,
      417.36,
      533.48
    ],
    "text": "vdJvjpu;ghu;g;Gf;fs;",
    "fonts": [
      "Kalaham"
    ],
    "sizes": [
      8.000005722045898
    ]
  },
  {
    "page_number": 2,
    "bbox": [
      112.71,
      463.12,
      294.57,
      477.54
    ],
    "text": "jdJ Mw;wy;fis ,dq;fhzy;jdJ Mw;wy;fis ,dq;fhzy;jdJ Mw;wy;fis ,dq;fhzy;jdJ Mw;wy;fis ,dq;fhzy;jdJ Mw;wy;fis ,dq;fhzy;",
    "fonts": [
      "Kalyani"
    ],
    "sizes": [
      14.000009536743164
    ]
  },
  {
    "page_number": 3,
    "bbox": [
      108.48,
      720.93,
      300.48,
      740.36
    ],
    "text": "4,ytr ghlE}y; tpepNahfj;jpw;fhf",
    "fonts": [
      "Kalaham",
      "Times-Roman"
    ],
    "sizes": [
      9.000006675720215,
      12.000008583068848
    ]
  },
  {
    "page_number": 3,
    "bbox": [
      108.48,
      135.09,
      486.48,
      259.05
    ],
    "text": "nfhLf;fg;gl;Ls;sd. nrad;Kiwj; njhopDl;gj;jpwd;> mofpaw; ghlq;fs;>fzpj tpQ;Qhdg; ghlq;fs; kw;Wk; nkhop rhu;e;j ghlq;fs; Nghd;wdghltpjhdj;jpDs; cl;gLj;jg;gl;bUg;gJk;> cq;fsplk; kiwe;Js;sjpwikfis ,dq;fz;L mtw;iw vjpu;fhyj;jpw;fhf Nkk;gLj;Jk;Nehf;fpNyahFk;. ghlrhiyapDs; ePq;fs; <LghL fhl;Lfpd;w,izg;ghltpjhd kw;Wk; ntspf;fsr; nraw;ghL %yKk; cq;fsJMw;wy;fs; jpwd;fis ,dq;fz;L mtw;iw tpUj;jp nra;J nfhs;tjw;FKbAk;.",
    "fonts": [
      "Kalaham"
    ],
    "sizes": [
      12.000008583068848
    ]
  },
  {
    "page_number": 3,
    "bbox": [
      108.48,
      271.05,
      486.45,
      347.13
    ],
    "text": "mNjNghd;W xUtuplk; jpwikfs;> Mw;wy;fs; vd;gd Vw;gLtjw;Fmtupd; guk;giuAk; nry;thf;Fr; nrYj;Jfpd;wJ vd mwpa Kbfpd;wJ.vdNt jd;dplk; fhzg;gLfpd;w Mw;wy;fis kpfr;rupahf ,dq;fhz;gJcq;fsJ vjpu;fhyj; njhopy; tho;f;ifia ntw;wpfukhf mikj;Jf;nfhs;tjw;F cWJizahf mikfpd;wJ.",
    "fonts": [
      "Kalaham"
    ],
    "sizes": [
      12.000008583068848
    ]
  },
  {
    "page_number": 3,
    "bbox": [
      108.48,
      365.92,
      291.69,
      380.34
    ],
    "text": "jkJ <LghLfis ,dq;fhzy;jkJ <LghLfis ,dq;fhzy;jkJ <LghLfis ,dq;fhzy;jkJ <LghLfis ,dq;fhzy;jkJ <LghLfis ,dq;fhzy;",
    "fonts": [
      "Kalaham",
      "Kalyani"
    ],
    "sizes": [
      12.000008583068848,
      14.000009536743164
    ]
  },
  {
    "page_number": 3,
    "bbox": [
      108.48,
      391.05,
      486.76,
      531.09
    ],
    "text": "cq;fs; Mw;wy;fis khj;jpuk; ,dq;fhz;gJ njhopy; Jiw xd;iwj;njupT nra;Jnfhs;tjw;Fg; NghJkhdjd;W. cq;fsplk; cs;s jpwikfspy;ePq;fs; kpfTk; tpUg;gk; fhl;Lk; Jiwapidj; njupT nra;a Ntz;Lk;.mjhtJ cq;fs; <Lghl;il kpfj; njspthf ,dq;fhz Ntz;Lk;.ve;jnthU nraiyAk; kpf ed;whfr; nra;J Kbg;gjw;F mJ njhlu;ghdtpUg;gKk;> MirAk; kl;LNk ,Uf;f Ntz;Lk;. jkf;F <Lghlw;w njhopypy;<LgLtjd;%yk; njhopy; jpUg;jpia mila KbahJ. ve;jnthUnjhopypdJk; ntw;wp my;yJ Njhy;tp jPu;khdpf;fg;gLk;NghJ njhopyhspapd; njhopy; jpUg;jp Kf;fpaj;Jtk; ngWfpwJ.",
    "fonts": [
      "Kalaham"
    ],
    "sizes": [
      12.000008583068848
    ]
  },
  {
    "page_number": 3,
    "bbox": [
      108.48,
      543.09,
      486.53,
      667.05
    ],
    "text": "ngUk;ghYk; ePq;fs; njhopy; Jiwnahd;iwj; njupT nra;Ak;NghJjw;NghJ kpfg; gpurpj;jpngw;Wf; fhzg;gLk; my;yJ mjpfkhNdhu; <LghLfhl;Lk; njhopw;JiwfisNa njupT nra;a tpUk;gf;$Lk;. Mdhy; cyfntw;wpahsu;fs; gyu; jkJ tpUg;gk;> Mw;wy; vd;gtw;Wf;fpilNa xd;iwnahd;W njhlu;GgLj;jpNa jkJ njhopy;fisj; Nju;e;njLj;Js;sdu;.vdNt cq;fs; tpUg;gj;Jf;F kl;Lk; ,lq;nfhLj;Njh my;yJ NtNwhUtu;njupT nra;jikf;fhfNth njhopy; xd;iwj; njupT nra;J nfhs;tJnghUj;jkw;wjhFk;.",
    "fonts": [
      "Kalaham"
    ],
    "sizes": [
      12.000008583068848
    ]
  },
  {
    "page_number": 3,
    "bbox": [
      108.48,
      679.05,
      486.7,
      707.13
    ],
    "text": "rkfhyj;jpy; njhopy; NjLeu;fspd; njhopy; <LghLfis ,dq;fz;Lnfhs;tjw;nfdg; gy El;gtiffs; ifahsg;gLfpd;wd. ~~njhopy; <Lghl;Lg;",
    "fonts": [
      "Kalaham"
    ],
    "sizes": [
      12.000008583068848
    ]
  },
  {
    "page_number": 4,
    "bbox": [
      294.48,
      720.93,
      486.47,
      740.36
    ],
    "text": "5,ytr ghlE}y; tpepNahfj;jpw;fhf",
    "fonts": [
      "Kalaham",
      "Times-Roman"
    ],
    "sizes": [
      9.000006675720215,
      12.000008583068848
    ]
  },
  {
    "page_number": 4,
    "bbox": [
      108.48,
      134.61,
      486.5,
      194.61
    ],
    "text": "gupNrhjid|| vDk; gupNrhjid Kiw ,tw;Ws; gpujhdkhdjhFk;.,jD}lhf toq;fg;gLfpd;w tpdhf;nfhj;Jf;F tpilaspg;gjd; %yk;xUtu; kpf tpUg;gk; fhl;lf;$ba njhopw;Jiwia ed;F ,dq;fz;Lnfhs;syhk;.",
    "fonts": [
      "Kalaham"
    ],
    "sizes": [
      12.000008583068848
    ]
  },
  {
    "page_number": 4,
    "bbox": [
      122.67,
      212.84,
      188.09,
      227.82
    ],
    "text": "nraw;ghL nraw;ghL nraw;ghL nraw;ghL nraw;ghL I",
    "fonts": [
      "Kalyani",
      "Times-Bold"
    ],
    "sizes": [
      14.000009536743164
    ]
  },
  {
    "page_number": 4,
    "bbox": [
      122.88,
      238.53,
      472.04,
      266.61
    ],
    "text": "~~njhopy; <Lghl;Lg; gupNrhjid|| njhlu;ghf cq;fs; MrpupaUld;fye;Jiuahb jfty;fisg; ngw;Wf; nfhs;Sq;fs;.",
    "fonts": [
      "Kalaham"
    ],
    "sizes": [
      12.000008583068848
    ]
  },
  {
    "page_number": 4,
    "bbox": [
      108.48,
      301.48,
      295.4,
      315.9
    ],
    "text": "vjpu;fhyj; njhopy; vjpu;ghu;f;ifvjpu;fhyj; njhopy; vjpu;ghu;f;ifvjpu;fhyj; njhopy; vjpu;ghu;f;ifvjpu;fhyj; njhopy; vjpu;ghu;f;ifvjpu;fhyj; njhopy; vjpu;ghu;f;if",
    "fonts": [
      "Kalaham",
      "Kalyani"
    ],
    "sizes": [
      12.000008583068848,
      14.000009536743164
    ]
  },
  {
    "page_number": 4,
    "bbox": [
      108.48,
      334.53,
      486.57,
      474.57
    ],
    "text": "ePq;fs; 9 Me; ju khztdhf ,Ue;j NghJk; cq;fsJ vjpu;fhyj;njhopy; njhlu;ghd VNjh xU vjpu;ghu;g;G my;yJ fw;gid cq;fsplk;,Uf;f KbAk;. rpy Ntis ,t;ntjpu;ghu;g;ghdJ fhyNthl;lj;jpy; khwTk;,lKz;L. rw;W rpe;jpj;Jg; ghUq;fs;. cq;fs; ,t;ntjpu;ghu;f;ifahdJcq;fs; jpwikAlDk; <LghLfSlDk; xj;JtUfpd;wjh? rkfhyj;jpy;ghlrhiyapy; fw;Fk; khztu;fspy; xU njhFjpapdu; cau; fy;tpapy;gpuNtrpg;gNjhL kw;nwhU njhFjpapdu; NtiyAyFf;Fs; gpuNtrpf;fpd;wdu;.cau;fy;tpf;Fj; njupTnra;ag;gltpy;iy vd;w fhuzj;jpw;fhf kl;Lk;xU khztd; jpwikaw;wtd; vdf; fUjg;gl KbahJ.",
    "fonts": [
      "Kalaham"
    ],
    "sizes": [
      12.000008583068848
    ]
  },
  {
    "page_number": 4,
    "bbox": [
      108.48,
      482.61,
      486.59,
      686.61
    ],
    "text": "cq;fs; jpwikfSf;Nfw;w njhopy; Jiwfis tpUj;jp nra;Jnfhs;tjw;fhd jifikfisg; G+uzg;gLj;j cjTk; mur> kw;Wk; jdpahu;epWtdq;fs; gy ehlshtpa uPjpapy; tpahgpj;Jf; fhzg;gLfpd;wd.me;epWtdq;fs; gw;wpr; rupahd mwpitg; ngw;wpUg;gJ cq;fSf;F kpfTk;Kf;fpakhFk;. ,J njhlu;gpy; cq;fSf;Fj; Njitahd MNyhridfistoq;fTk;> topfhl;lTk; jk;ik mu;g;gzpj;Js;s cj;jpNahfj;ju;fs; kw;Wk;epWtdq;fs; gy ,Ug;gij ePq;fs; mwpe;jpUf;fyhk;. NkYk; ,t;thwhdMNyhridfs; Clhf ePq;fs; vjpu;ghu;g;gJ Nghd;W cau;fy;tpngWtjw;fhf gy;fiyf;fofk; EioAk; re;ju;g;gKk; fpilf;fyhk;.,yq;ifapy; jpwe;j gy;fiyf;fofk; Nghd;w epWtdq;fs; ,e;Nehf;fpNyNaepWtg;gl;Ls;sd. mt;thNw ,yq;ifapYs;s ve;jnthUgy;fiyf;fofj;jpYk; ntspthup khztuhfg; gjpT nra;J cau;fy;tpiag;ngw;Wf; nfhs;Sk; tha;g;Gk; fhzg;gLfpd;wJ.",
    "fonts": [
      "Kalaham"
    ],
    "sizes": [
      12.000008583068848
    ]
  },
  {
    "page_number": 5,
    "bbox": [
      108.48,
      720.93,
      300.48,
      740.36
    ],
    "text": "6,ytr ghlE}y; tpepNahfj;jpw;fhf",
    "fonts": [
      "Kalaham",
      "Times-Roman"
    ],
    "sizes": [
      9.000006675720215,
      12.000008583068848
    ]
  },
  {
    "page_number": 5,
    "bbox": [
      246.48,
      139.57,
      348.75,
      157.08
    ],
    "text": "njhopw; gapw;rpnjhopw; gapw;rpnjhopw; gapw;rpnjhopw; gapw;rpnjhopw; gapw;rp",
    "fonts": [
      "Kalaham",
      "Kalyani"
    ],
    "sizes": [
      12.000008583068848,
      17.000011444091797
    ]
  },
  {
    "page_number": 5,
    "bbox": [
      108.48,
      184.29,
      486.47,
      244.29
    ],
    "text": "njhopy; vjpu;ghu;g;GfSf;fhfj; njhopw; gapw;rp toq;fg;gLtjd;Kf;fpa Nehf;fk; njhopnyhd;wpy; <LgLtjw;Fj; Njitahd mwpT> Nju;r;rpfs; kw;Wk; Mw;wy;fis toq;FtJk; njhopy;fs; njhlu;ghd rpwe;jkdg;ghq;if tpUj;jp nra;tJkhFk;.",
    "fonts": [
      "Kalaham"
    ],
    "sizes": [
      12.000008583068848
    ]
  },
  {
    "page_number": 5,
    "bbox": [
      108.48,
      264.21,
      486.54,
      452.25
    ],
    "text": "gy;NtW Nju;r;rpfisj; jd;dfj;Nj nfhz;l gilg;ghw;wy; kpf;ftu;fSf;NfNtiyAyfpDs; mjpf Nfs;tp fhzg;gLfpd;wJ. ,f;Nfs;tpahdJ cs;ehl;bYk;> ru;tNjr kl;lj;jpYk; fhzg;gLfpd;wJ. NtiyAyfpy; gpuNtrpg;gjw;Fj; Njitahd Nju;r;rpfisg; ngw;Wf; nfhs;tjw;F rpwe;j topnjhopw;gapw;rp ghlnewpfisg; gapy;tjhFk;. ,r;re;ju;g;gj;jpy; NkNyAs;sge;jpapy; Fwpg;gplg;gl;Ls;sJ Nghd;W cq;fs; Mw;wy;> <LghL> vjpu;ghu;g;Gvd;gtw;Wf;Fg; nghUj;jkhd njhopy; xd;iw Nehf;fhff; nfhz;lghlnewpnahd;iwj; njupT nra;tJ nghUj;jkhdjhFk;. ,t;thwhdghlnewp xd;iwj; njupT nra;Akplj;J ,g;ghl newpAld; njhlu;ghdnjhopy; tha;g;Gfs; gw;wpa gpd;dzpj; jfty;fis mwpe;jpUg;gJk;Kf;fpakhFk;. mjhtJ mj;Jiwapd; njhopYf;fhd Nfs;tp NtiyAyfpy;fhzg;gLfpd;wjh? vd;gJ Nghd;w tplaq;fisj; Njbg;ghu;f;f Ntz;Lk;.",
    "fonts": [
      "Kalaham"
    ],
    "sizes": [
      12.000008583068848
    ]
  },
  {
    "page_number": 5,
    "bbox": [
      108.48,
      464.25,
      486.51,
      588.21
    ],
    "text": ",g;gapw;rp newpfs; mur kw;Wk; jdpahu; epWtdq;fs; %yk;toq;fg;gl KbAk;. vdpDk; kpf cau;e;j juj;ijAilaJk; ru;tNjrmq;fPfhuj;ijg; ngw;wJkhd rpwe;j gapw;rpfis toq;Ftij Nehf;fhff;nfhz;L murhq;fk; Njrpa njhopw;jifikr; rl;lfk; xd;iw mwpKfg;gLj;jpAs;sJ. ,jd;fPo; Njrpa njhopw;jifik rhd;wpjo; (NVQ) toq;fg;gLtJld; ,jw;nfd 7 Nju;r;rp kl;lq;fSk; mwpKfg;gLj;jg;gl;Ls;sd.mz;ikapy; mikf;fg;gl;l njhopDl;gg; gy;fiyf;fofj;ij ,jd; etPdfl;lkhf mwpKfg;gLj;j KbAk;.",
    "fonts": [
      "Kalaham",
      "Times-Roman"
    ],
    "sizes": [
      12.000008583068848
    ]
  },
  {
    "page_number": 6,
    "bbox": [
      294.48,
      720.93,
      486.47,
      740.36
    ],
    "text": "7,ytr ghlE}y; tpepNahfj;jpw;fhf",
    "fonts": [
      "Kalaham",
      "Times-Roman"
    ],
    "sizes": [
      9.000006675720215,
      12.000008583068848
    ]
  },
  {
    "page_number": 6,
    "bbox": [
      122.88,
      358.53,
      472.05,
      386.61
    ],
    "text": "njhopw;gapw;rp ghlnewp njhlu;ghd jfty;fisg; ngw;Wf;nfhs;sf;$ba mur epWtdq;fs; rpy gpd;tUkhW",
    "fonts": [
      "Kalaham"
    ],
    "sizes": [
      12.000008583068848
    ]
  },
  {
    "page_number": 6,
    "bbox": [
      144.48,
      403.64,
      464.76,
      466.53
    ],
    "text": "\u2666njhopDl;gf; fy;tp kw;Wk; gapw;rpj; jpizf;fsk;\u2666Njrpa gapYdu; kw;Wk; njhopw; gapw;rp mjpfhu rig\u2666njhopw; gapw;rp mjpfhu rig\u2666Njrpa ,isQu; Nritfs; kd;wk;",
    "fonts": [
      "Kalaham",
      "Symbol"
    ],
    "sizes": [
      12.000008583068848
    ]
  },
  {
    "page_number": 6,
    "bbox": [
      108.48,
      486.57,
      486.48,
      514.53
    ],
    "text": "mur Jiwf;F Nkyjpfkhf jdpahu; kw;Wk; mur rhu;gw;wepWtdq;fspdhy; elhj;jg;gLfpd;w ghlnewpfs; mjpfk; fhzg;gLfpd;wd.",
    "fonts": [
      "Kalaham"
    ],
    "sizes": [
      12.000008583068848
    ]
  },
  {
    "page_number": 6,
    "bbox": [
      108.48,
      526.53,
      486.48,
      570.57
    ],
    "text": ",t;thwhd ghlnewpfisj; njupT nra;Ak;NghJ cupa epWtdk;Njrpa juj;Jf;Fg; nghUe;jf; $ba Kiwapy; mike;j epWtdkh?vd;gijf; fz;lwpa Ntz;Lk;.",
    "fonts": [
      "Kalaham"
    ],
    "sizes": [
      12.000008583068848
    ]
  },
  {
    "page_number": 6,
    "bbox": [
      108.48,
      614.61,
      486.54,
      690.57
    ],
    "text": "jhk; tpUk;Gk; njhopypy; gpuNtrpg;gjw;Fj; Njitahd gapw;rpfisg;ngw;Wf; nfhz;ljd; gpd;du; mj; njhopypy; gpuNtrpj;jy; mtrpakhFk;.cq;fs; tho;f;ifj; njhopyhdJ cq;fs; vjpu;fhy tho;tpd; ntw;wpNjhy;tpia epu;zapf;ff;$ba xU gpujhd fhuzp vd;gij ePq;fs; kwe;Jtplf;$lhJ.",
    "fonts": [
      "Kalaham"
    ],
    "sizes": [
      12.000008583068848
    ]
  },
  {
    "page_number": 6,
    "bbox": [
      117.89,
      138.09,
      303.55,
      151.48
    ],
    "text": "Njrpa njhopw;wfikr; rl;lfk;Njrpa njhopw;wfikr; rl;lfk;Njrpa njhopw;wfikr; rl;lfk;Njrpa njhopw;wfikr; rl;lfk;Njrpa njhopw;wfikr; rl;lfk;",
    "fonts": [
      "Kalaham"
    ],
    "sizes": [
      13.000009536743164
    ]
  },
  {
    "page_number": 6,
    "bbox": [
      146.04,
      335.2,
      443.89,
      345.21
    ],
    "text": "njhopy; rhu; kw;Wk; njhopy; jpwd;fs; Mizf;FO TVET GUIDE 2009",
    "fonts": [
      "Kalaham",
      "Times-Roman"
    ],
    "sizes": [
      10.000007629394531
    ]
  },
  {
    "page_number": 6,
    "bbox": [
      114.72,
      284.64,
      165.0,
      292.64
    ],
    "text": "1.Mk;gbKiw",
    "fonts": [
      "Kalaham"
    ],
    "sizes": [
      8.000005722045898
    ]
  },
  {
    "page_number": 6,
    "bbox": [
      160.8,
      261.0,
      205.8,
      269.0
    ],
    "text": "2.Mk;gbKiw",
    "fonts": [
      "Kalaham"
    ],
    "sizes": [
      8.000005722045898
    ]
  },
  {
    "page_number": 6,
    "bbox": [
      197.76,
      242.52,
      242.76,
      250.52
    ],
    "text": "3.Mk;gbKiw",
    "fonts": [
      "Kalaham"
    ],
    "sizes": [
      8.000005722045898
    ]
  },
  {
    "page_number": 6,
    "bbox": [
      238.44,
      222.24,
      283.44,
      230.24
    ],
    "text": "4.Mk;gbKiw",
    "fonts": [
      "Kalaham"
    ],
    "sizes": [
      8.000005722045898
    ]
  },
  {
    "page_number": 6,
    "bbox": [
      275.52,
      201.36,
      320.52,
      209.36
    ],
    "text": "5.Mk;gbKiw",
    "fonts": [
      "Kalaham"
    ],
    "sizes": [
      8.000005722045898
    ]
  },
  {
    "page_number": 6,
    "bbox": [
      314.88,
      179.52,
      359.88,
      187.52
    ],
    "text": "6.Mk;gbKiw",
    "fonts": [
      "Kalaham"
    ],
    "sizes": [
      8.000005722045898
    ]
  },
  {
    "page_number": 6,
    "bbox": [
      361.68,
      162.6,
      406.68,
      170.6
    ],
    "text": "7.Mk;gbKiw",
    "fonts": [
      "Kalaham"
    ],
    "sizes": [
      8.000005722045898
    ]
  },
  {
    "page_number": 6,
    "bbox": [
      366.96,
      178.56,
      471.85,
      191.96
    ],
    "text": "jpl;lkplyhsu;fs;gl;ljhup epiy",
    "fonts": [
      "Kalaham"
    ],
    "sizes": [
      8.000005722045898
    ]
  },
  {
    "page_number": 6,
    "bbox": [
      289.56,
      199.2,
      471.01,
      229.4
    ],
    "text": "Kfhikahsu;fs;bg;Nshkh epiy Nkw;ghu;itahsu;fs;",
    "fonts": [
      "Kalaham"
    ],
    "sizes": [
      8.000005722045898
    ]
  },
  {
    "page_number": 6,
    "bbox": [
      253.44,
      241.32,
      392.15,
      249.32
    ],
    "text": "RNal;irahfr; nraw;gl KbAkhNdhu;",
    "fonts": [
      "Kalaham"
    ],
    "sizes": [
      8.000005722045898
    ]
  },
  {
    "page_number": 6,
    "bbox": [
      154.08,
      302.64,
      304.08,
      310.64
    ],
    "text": "mbg;gil kw;Wk; Muk;g Mw;wYilNahu;",
    "fonts": [
      "Kalaham"
    ],
    "sizes": [
      8.000005722045898
    ]
  },
  {
    "page_number": 6,
    "bbox": [
      189.72,
      273.96,
      469.32,
      290.72
    ],
    "text": "rhd;wpjo; epiynjhlu;e;J Nkw;ghu;itahsupd; fPo; nraw;gLNthu;",
    "fonts": [
      "Kalaham"
    ],
    "sizes": [
      8.000005722045898
    ]
  },
  {
    "page_number": 6,
    "bbox": [
      225.48,
      262.2,
      417.48,
      270.2
    ],
    "text": "rpW Nkw;ghu;itahsupd; fPo; nrayhw;w KbAkhNdhu;",
    "fonts": [
      "Kalaham"
    ],
    "sizes": [
      8.000005722045898
    ]
  },
  {
    "page_number": 6,
    "bbox": [
      113.91,
      588.52,
      292.08,
      602.94
    ],
    "text": "njhopnyhd;iwj; Nju;e;njLj;jy;njhopnyhd;iwj; Nju;e;njLj;jy;njhopnyhd;iwj; Nju;e;njLj;jy;njhopnyhd;iwj; Nju;e;njLj;jy;njhopnyhd;iwj; Nju;e;njLj;jy;",
    "fonts": [
      "Kalyani"
    ],
    "sizes": [
      14.000009536743164
    ]
  },
  {
    "page_number": 7,
    "bbox": [
      108.48,
      720.93,
      300.48,
      740.36
    ],
    "text": "8,ytr ghlE}y; tpepNahfj;jpw;fhf",
    "fonts": [
      "Kalaham",
      "Times-Roman"
    ],
    "sizes": [
      9.000006675720215,
      12.000008583068848
    ]
  },
  {
    "page_number": 7,
    "bbox": [
      108.48,
      134.61,
      486.47,
      226.53
    ],
    "text": "cq;fSf;Fg; nghUj;jkhd njhopw;Jiw xd;iwj; njupT nra;Ak;NghJ> mJ njhlu;ghfj; jPu;khdk; vLf;fg; nghUj;jkhdtu; ePq;fNs.vdpDk; cq;fshy; jdpj;Jj; jPu;khdk; Nkw;nfhs;tjw;Fr; rpuknkdpy;>mjw;F cjtp nra;af;$ba gyjug;gl;l Nritfs; vkJ ehl;by;fhzg;gLfpd;wd. ,it ~~njhopy; topfhl;ly; Nrit|| vd mwpKfg;gLj;jg;gl;Ls;sd.",
    "fonts": [
      "Kalaham"
    ],
    "sizes": [
      12.000008583068848
    ]
  },
  {
    "page_number": 7,
    "bbox": [
      108.48,
      238.53,
      486.65,
      346.53
    ],
    "text": "njhopy; topfhl;ly; Nritapd; gpujhd Nehf;fk;> kdpj tsq;fiskpfg; gad; kpf;fjhfj; Njrpa cw;gj;jpf;Fg; gad;gLj;JtjhFk;. ,t;thwhdepiyaq;fs; njhopy; ,y;yk;> gpuNjr nrayfk; kw;Wk; khfhzrigfspYk; mikf;fg;gl;Ls;sd. ,k;kj;jpa epiyaq;fspy; ,Ue;Jcs;ehl;L> ntspehl;L Ntiytha;g;Gfs; njhlu;ghd jfty;fisg; ngw;Wf;nfhs;s KbtJld;> ,jw;fhd topfhl;ly;fs;> MNyhridfistoq;ff;$ba mjpfhupfSk; ,e;epiyaq;fspy; flikahw;Wfpd;wdu;.",
    "fonts": [
      "Kalaham"
    ],
    "sizes": [
      12.000008583068848
    ]
  },
  {
    "page_number": 7,
    "bbox": [
      122.88,
      366.57,
      472.0,
      442.53
    ],
    "text": "njhopy; xd;iwj; Njbf;nfhs;tjw;F gad;gLj;j KbAkhdtopKiwfs; gy fhzg;gLfpd;wd mitahtd.mur tu;j;jkhdp mwptpj;jy;ehshe;j> thuhe;j nra;jpj;jhs;fspd; njhopy; tha;g;Gg; gFjp~~Jops Net|| (WWW.jobsnet.lk) vd;w ,izaj;jsk;",
    "fonts": [
      "Kalaham",
      "Times-Roman"
    ],
    "sizes": [
      12.000008583068848
    ]
  },
  {
    "page_number": 7,
    "bbox": [
      346.2,
      565.84,
      454.19,
      575.85
    ],
    "text": "\"Jobs Net\" ,izaj;jsk;",
    "fonts": [
      "Kalaham",
      "Times-Roman"
    ],
    "sizes": [
      10.000007629394531
    ]
  },
  {
    "page_number": 7,
    "bbox": [
      132.36,
      593.44,
      200.63,
      603.44
    ],
    "text": "mur tu;j;jkhdp",
    "fonts": [
      "Kalaham"
    ],
    "sizes": [
      10.000007629394531
    ]
  },
  {
    "page_number": 7,
    "bbox": [
      259.44,
      693.28,
      336.79,
      703.28
    ],
    "text": "ntw;wpl tpsk;guk;",
    "fonts": [
      "Kalaham"
    ],
    "sizes": [
      10.000007629394531
    ]
  },
  {
    "page_number": 7,
    "bbox": [
      257.64,
      581.25,
      355.91,
      594.76
    ],
    "text": "'''''''''gjtp ntw;wplq;fs;",
    "fonts": [
      "FMAbhaya",
      "Kalaham"
    ],
    "sizes": [
      12.000008583068848
    ]
  },
  {
    "page_number": 8,
    "bbox": [
      294.48,
      720.93,
      486.47,
      740.36
    ],
    "text": "9,ytr ghlE}y; tpepNahfj;jpw;fhf",
    "fonts": [
      "Kalaham",
      "Times-Roman"
    ],
    "sizes": [
      9.000006675720215,
      12.000008583068848
    ]
  },
  {
    "page_number": 8,
    "bbox": [
      122.67,
      132.92,
      472.1,
      210.57
    ],
    "text": "nraw;ghLnraw;ghLnraw;ghLnraw;ghLnraw;ghL IImurtu;j;jkhdp mwptpj;jy;> nra;jpg; gj;jpupifapd; njhopy; tha;g;Gg;gFjp vd;gtw;iwg; guprPypj;J> gy;NtW Jiwfspd;fPo; fhzg;gLk;njhopy;fis tifg;gLj;Jq;fs;. tha;g;gpUe;jhy; ,izaj;jsj;ijg;guprPyid nra;Aq;fs;.",
    "fonts": [
      "Kalaham",
      "Kalyani",
      "Times-Bold"
    ],
    "sizes": [
      12.000008583068848,
      14.000009536743164
    ]
  },
  {
    "page_number": 8,
    "bbox": [
      108.27,
      245.44,
      174.7,
      259.86
    ],
    "text": "Ranjhopy; Ranjhopy; Ranjhopy; Ranjhopy; Ranjhopy;",
    "fonts": [
      "Kalyani"
    ],
    "sizes": [
      14.000009536743164
    ]
  },
  {
    "page_number": 8,
    "bbox": [
      108.48,
      270.57,
      486.48,
      410.61
    ],
    "text": "~~jd;dplKs;s Mw;wy;fs;> tpUg;gq;fs; kw;Wk; tsq;fisg;gad;gLj;jp jdf;nfd nrhe;jkhd Kaw;rpnahd;iw Muk;gpj;jy;|| Ranjhopy; vd mwpKfg;gLj;jg;gLfpd;wJ. vdpDk; rkfhyj;jpy; ~~Ranjhopy;||vDk; vz;zf;fUtpw;Fg; gjpyhf Kaw;rpahz;ik vd;w vz;zf;fUNjhd;wpAs;sJ. Kaw;rpahz;ikahsu; vd;gtu; r%fj;jpd; NjitfSf;Fg;nghUe;Jk; tifapYk; Mf;fj;jpwd; ntspg;gLk; tifapYk;Ranjhopnyhd;iw Muk;gpf;Fk; eguhthu;. rkfhyj;jpy; fhzg;gLk;Vuhskhd ntw;wpfukhd tpahghuq;fs;> Kaw;rpahz;ik vz;zf;fUtpD}lhfNt ntw;wp ,yf;if mile;Js;sd.",
    "fonts": [
      "Kalaham"
    ],
    "sizes": [
      12.000008583068848
    ]
  },
  {
    "page_number": 8,
    "bbox": [
      108.48,
      422.61,
      486.46,
      466.53
    ],
    "text": "~~tUlj;jpd; rpwe;j Kaw;rpahsu;|| vd;w tpUijg; ngw;Wf; nfhz;lMfpg; m`kl; mtu;fs; jdJ ntw;wpf;fhd ,ufrpaj;ij gj;jpupifepUgu; xUtUf;Fg; gpd;tUkhW tpgupf;fpwhu;.",
    "fonts": [
      "Kalaham"
    ],
    "sizes": [
      12.000008583068848
    ]
  },
  {
    "page_number": 8,
    "bbox": [
      108.48,
      478.53,
      486.58,
      602.61
    ],
    "text": "~~ehd; cau;jug; guPl;iria Kbj;Jtpl;L tPl;bypUf;Fk; fhyj;jpNyNa vdJ tPl;Lj; Njhl;lj;ij moFgLj;j Ntz;Lk; vd;w vz;zk;cUthdJ. ehd; rhjhuz ju tFg;gpy; tptrha ghlk; fw;wjhy; ,r;nray;vdf;F ,yFthf ,Ue;jJ. vdJ mk;kh> mg;gh> mf;fh MfpNahu;,t;tplaj;jpy; vdf;F Cf;fj;ijAk;> toq;fpdhu;fs;. ehd; vkJ Njhl;lj;ijvdf;Fj; njupe;j Kiwapy; jpl;lkpl;L moFgLj;jpNdd;. midtUk;vdJ tPl;Lj;Njhl;lk; mofhf cs;sJ vdg; Gfo;e;J $wpa NghJ ehd;kpfTk; kfpo;r;rpaile;Njd;.",
    "fonts": [
      "Kalaham"
    ],
    "sizes": [
      12.000008583068848
    ]
  },
  {
    "page_number": 8,
    "bbox": [
      108.48,
      614.61,
      486.49,
      706.53
    ],
    "text": ",jw;fpilapNyNa cau;jug; guPl;irg; ngWNgWfs; ntspahfpd.vdf;Fg; gy;fiyf;fofk; Eiotjw;fhf Nghjpa Gs;spfs; fpilf;ftpy;iy.cz;ikapNyNa vdf;F kpfTk; ftiy Vw;gl;lJ. vd;whYk; ehd;ek;gpf;if ,of;ftpy;iy. vdJ Mw;wy;fisg; gad;gLj;jp mit %yk;cr;rg; gaidg; ngwNtz;Lnkd vz;zpNdd;. vdJ ghlrhiy tptrhaMrpupiaapd; topfhl;lypd; fPo; ehd; jdpahu; epWtdnkhd;wpdhy;",
    "fonts": [
      "Kalaham"
    ],
    "sizes": [
      12.000008583068848
    ]
  },
  {
    "page_number": 9,
    "bbox": [
      108.48,
      720.93,
      303.48,
      740.36
    ],
    "text": "10,ytr ghlE}y; tpepNahfj;jpw;fhf",
    "fonts": [
      "Kalaham",
      "Times-Roman"
    ],
    "sizes": [
      9.000006675720215,
      12.000008583068848
    ]
  },
  {
    "page_number": 9,
    "bbox": [
      108.48,
      134.61,
      486.89,
      482.61
    ],
    "text": "elhj;jg;gLk; ~~G+q;fh moFgLj;jy;|| vd;w ghlnewpnahd;iwg; gpd;gw;wpNdd;.mjd; gpd; rhjhuz fl;lzk; xd;iw mwtpl;L vdf;F mwpKfkhdtu;fs;kw;Wk; cwtpdu;fspd; tPl;Lj;Njhl;lq;fis moFgLj;jpf;nfhLj;Njd;. mjd;%yk;fpilf;fg;ngw;w gzj;ijf;nfhz;L vdf;F mtrpakhdcgfuzq;fs; gytw;iwthq;fpf; nfhs;s Kbe;jJ.ehd; fw;w epWtdj;jpd;MNyhridg; gb vdf;Ftpahghu epWt dkhf gjpTnra;J fld; njhifnahd;iwngw;Wf; nfhs;s Kbe;jJ.,jd; gpd;du; tuNtw;Gkz;lgq;fs;> cy;yhrg; gaz tpLjpfs; Nghd;w epWtdq;fspy; Njhl;lmyq;fhu NtiyfSf;fhf fl;lisfs; vdf;Ff; fpilj;jd. Muk;gj;jpy;vdf;F ,uT gfy; ghuhJ rpukg;gl;L Ntiy nra;a Ntz;ba epiyVw;gl;lJ. ,d;W vdf;F ntspehLfspypUe;J $l Njhl;l myq;fhuj;Jf;fhdfl;lisfs; fpilf;fg;ngWfpd;wd. ,e; ehLfspy; vdJ epWtdj;jpd; fpisfs;fhzg;gLfpd;wd. mjpfkhNdhUf;Fj; njhopy;tha;g;Gf;fis ngw;Wf;nfhLf;fTk; Kbe;Js;sJ.",
    "fonts": [
      "Kalaham"
    ],
    "sizes": [
      12.000008583068848
    ]
  },
  {
    "page_number": 9,
    "bbox": [
      108.48,
      494.61,
      486.44,
      522.57
    ],
    "text": ",t;tpUJ vdJ Kaw;rpf;Fk; mu;g;gzpg;Gf;Fk; fpilj;j ngWkjpkpf;f kjpg;gPL vd ehd; vz;ZfpNwd;.",
    "fonts": [
      "Kalaham"
    ],
    "sizes": [
      12.000008583068848
    ]
  },
  {
    "page_number": 9,
    "bbox": [
      122.67,
      557.44,
      196.32,
      571.86
    ],
    "text": "nraw;ghLnraw;ghLnraw;ghLnraw;ghLnraw;ghL III",
    "fonts": [
      "Kalaham",
      "Kalyani",
      "Times-Bold"
    ],
    "sizes": [
      12.000008583068848,
      14.000009536743164
    ]
  },
  {
    "page_number": 9,
    "bbox": [
      122.88,
      590.61,
      472.07,
      634.53
    ],
    "text": "Nkw;$wg;gl;l rk;gtj;ij ed;F thrpj;J Kaw;rpahz;ikahsu;vd;w tifapy; ntw;wpailtjw;F Mfpg; m`kl; ,lk; fhzg;gl;ltpNrl Fzhk;rq;fisg; gl;baw;gLj;Jq;fs;.",
    "fonts": [
      "Kalaham"
    ],
    "sizes": [
      12.000008583068848
    ]
  },
  {
    "page_number": 9,
    "bbox": [
      363.36,
      336.88,
      397.08,
      349.16
    ],
    "text": "cU 6'4",
    "fonts": [
      "FMAbabld",
      "Kalaham"
    ],
    "sizes": [
      10.000007629394531
    ]
  },
  {
    "page_number": 10,
    "bbox": [
      291.48,
      720.93,
      486.47,
      740.36
    ],
    "text": "11,ytr ghlE}y; tpepNahfj;jpw;fhf",
    "fonts": [
      "Kalaham",
      "Times-Roman"
    ],
    "sizes": [
      9.000006675720215,
      12.000008583068848
    ]
  },
  {
    "page_number": 10,
    "bbox": [
      163.41,
      134.66,
      432.03,
      151.14
    ],
    "text": "6.2 njhopy; mgptpUj;jpf;fhd topKiwfs;6.2 njhopy; mgptpUj;jpf;fhd topKiwfs;6.2 njhopy; mgptpUj;jpf;fhd topKiwfs;6.2 njhopy; mgptpUj;jpf;fhd topKiwfs;6.2 njhopy; mgptpUj;jpf;fhd topKiwfs;",
    "fonts": [
      "Kalyani"
    ],
    "sizes": [
      14.000009536743164,
      16.000011444091797
    ]
  },
  {
    "page_number": 10,
    "bbox": [
      108.48,
      170.61,
      486.5,
      230.61
    ],
    "text": "Ranjhopy; my;yJ NtW ve;jnthU njhopy; ClhfTk;NtiyAyfj;jpw;Fg; gpuNtrpg;gtu; njhopyhsu; vdf; fUjg;gLfpd;wdu;.njhopyhsu; xUtu; rpwe;jnjhU njhopyhsuhf kpspu gy fhuzpfs;nry;thf;Fr; nrYj;Jfpd;wd. mtw;iwg; gpd;tUkhW tifg;gLj;jyhk;.",
    "fonts": [
      "Kalaham"
    ],
    "sizes": [
      12.000008583068848
    ]
  },
  {
    "page_number": 10,
    "bbox": [
      108.48,
      249.4,
      320.13,
      263.82
    ],
    "text": "rpwe;j kd xw;WikAk; mu;g;gzpg;Gk;rpwe;j kd xw;WikAk; mu;g;gzpg;Gk;rpwe;j kd xw;WikAk; mu;g;gzpg;Gk;rpwe;j kd xw;WikAk; mu;g;gzpg;Gk;rpwe;j kd xw;WikAk; mu;g;gzpg;Gk;",
    "fonts": [
      "Kalaham",
      "Kalyani"
    ],
    "sizes": [
      12.000008583068848,
      14.000009536743164
    ]
  },
  {
    "page_number": 10,
    "bbox": [
      108.48,
      274.53,
      486.46,
      366.57
    ],
    "text": "jhd; Nkw;nfhs;fpd;w ve;jnthU fhupaj;ijAk; kd xUikg;ghl;LlDk; mu;g;gzpg;GlDk; Nkw;nfhs;s Ntz;Lk;. ,d;W nra;a Ntz;bagzpia ehis nra;ayhk; vdf; fhye;jho;j;jhJ> fpilf;fpd;w tsq;fiscr;rkhfg; gad;gLj;jp cupa fhupaj;ij epiwNtw;WtJ rpwe;j njhopyhsupd; gz;ghFk;. mt;thNw jk;khy; nra;ag;gLfpd;w fhupaq;fspd;juj;ijg; Ngzpg; ghJfhg;gjpy; ftdk; nrYj;JtJk; Kf;fpakhFk;.",
    "fonts": [
      "Kalaham"
    ],
    "sizes": [
      12.000008583068848
    ]
  },
  {
    "page_number": 10,
    "bbox": [
      108.68,
      377.44,
      345.73,
      391.86
    ],
    "text": "njhopy; jpUg;jpia Vw;gLj;jpf; nfhs;sy;njhopy; jpUg;jpia Vw;gLj;jpf; nfhs;sy;njhopy; jpUg;jpia Vw;gLj;jpf; nfhs;sy;njhopy; jpUg;jpia Vw;gLj;jpf; nfhs;sy;njhopy; jpUg;jpia Vw;gLj;jpf; nfhs;sy;",
    "fonts": [
      "Kalaham",
      "Kalyani"
    ],
    "sizes": [
      13.000009536743164,
      14.000009536743164
    ]
  },
  {
    "page_number": 10,
    "bbox": [
      108.48,
      402.57,
      486.63,
      542.61
    ],
    "text": "jdJ njhopy; kw;Wk; njhopy; epiyak; njhlu;ghf rpwe;jkdg;ghd;ikia Vw;gLj;jpf; nfhs;tjhdJ njhopnyhd;iw ntw;wpailar;nra;tjpy; nry;thf;Fr; nrYj;Jfpd;wJ. jhd; nra;fpd;w njhopiyj; jpdKk;tpku;rpj;Jf; nfhz;L NtW njhopy;fs; njhlu;ghd fw;gidapy; ,Ug;Nghu;,d;W r%fj;jpy; Vuhskhf cs;sdu;. ,tu;fs; xUNghJk; rpwe;jnjhUnjhopyhsuhf tu KbahJ. jdJ njhopy; kw;Wk; mjd; gpd;dzpfisrpwg;ghfTk;> kfpo;r;rpfukhfTk; itj;Jf; nfhs;Sk; jpwik nfhz;ltNujdJ njhopy; njhlu;ghd rpwe;j kdg;ghq;Fld; $ba Mj;k jpUg;jpAld;jdJ njhopiy epiwNtw;Wthu;.",
    "fonts": [
      "Kalaham"
    ],
    "sizes": [
      12.000008583068848
    ]
  },
  {
    "page_number": 10,
    "bbox": [
      108.48,
      561.4,
      390.71,
      575.82
    ],
    "text": "Nrit toq;Fdu;fspd; Njitfis epiwNtw;wy;Nrit toq;Fdu;fspd; Njitfis epiwNtw;wy;Nrit toq;Fdu;fspd; Njitfis epiwNtw;wy;Nrit toq;Fdu;fspd; Njitfis epiwNtw;wy;Nrit toq;Fdu;fspd; Njitfis epiwNtw;wy;",
    "fonts": [
      "Kalaham",
      "Kalyani"
    ],
    "sizes": [
      12.000008583068848,
      14.000009536743164
    ]
  },
  {
    "page_number": 10,
    "bbox": [
      108.48,
      594.57,
      486.49,
      702.57
    ],
    "text": "NtiyAyfpDs; Eiofpd;w rfyUf;Fk;> NtiyAyif ,af;Ffpd;wegu;fspd;> mjhtJ Nrit toq;Fdu;fspd; Njitfis epiwNtw;WtJ,d;wpaikahjjhFk;. mt;thwpd;Nwy; gy;NtW gpur;rpidfs; Njhd;wf;$Lk;.Nrit toq;Fdu;fs; vg;NghJk; nghWg;Gld; jkJ flikfisepiwNtw;Wfpd;w> epWtdj;Jf;F tpRthrkhd Neu;ikahd fhuparpj;jpAila xOf;fKs;s njhopyhsu;fisNa tpUk;Gfpd;wdu;. ,Nj Nghd;WnghJ Nehf;fKs;s epWtdj;jpd; Njitfisr; rpwg;ghf epiwNtw;Wfpd;w",
    "fonts": [
      "Kalaham"
    ],
    "sizes": [
      12.000008583068848
    ]
  },
  {
    "page_number": 11,
    "bbox": [
      108.48,
      720.93,
      303.48,
      740.36
    ],
    "text": "12,ytr ghlE}y; tpepNahfj;jpw;fhf",
    "fonts": [
      "Kalaham",
      "Times-Roman"
    ],
    "sizes": [
      9.000006675720215,
      12.000008583068848
    ]
  },
  {
    "page_number": 11,
    "bbox": [
      108.48,
      134.61,
      486.45,
      162.57
    ],
    "text": "njhopyhsu;fNs me;epWtdj;jpw;F kpfTk; Ntz;lg; gl;ltu;fshfTk;khWfpd;wdu;.",
    "fonts": [
      "Kalaham"
    ],
    "sizes": [
      12.000008583068848
    ]
  },
  {
    "page_number": 11,
    "bbox": [
      108.68,
      181.48,
      400.54,
      195.9
    ],
    "text": "Nrit ngWeu;fspd; Njitfisj; jpUg;jpg;gLj;jy;Nrit ngWeu;fspd; Njitfisj; jpUg;jpg;gLj;jy;Nrit ngWeu;fspd; Njitfisj; jpUg;jpg;gLj;jy;Nrit ngWeu;fspd; Njitfisj; jpUg;jpg;gLj;jy;Nrit ngWeu;fspd; Njitfisj; jpUg;jpg;gLj;jy;",
    "fonts": [
      "Kalaham",
      "Kalyani"
    ],
    "sizes": [
      13.000009536743164,
      14.000009536743164
    ]
  },
  {
    "page_number": 11,
    "bbox": [
      108.48,
      206.61,
      486.58,
      314.61
    ],
    "text": "Ntiy cyfpy; Kaw;rpahsu; xUtu; gpujhdkhf gz;lq;fs; kw;Wk;Nritfspd; cw;gj;jpA+lhf kf;fspd; Njitfis epiwNtw;Wgtuhthu;.,q;F thbf;ifahsu;fspd; Njitfisr; rupahf epiwNtw;w KbahjepWtdk; gaDWjp tha;e;j epWtdkhf khl;lhJ. gz;lj;jpd; my;yJNritapd; juk; vd;gJ Efu;Nthdpd; Njitf;F Vw;g jukhf> cupaNeuj;jpw;F mg;nghUis my;yJ Nritia toq;FtjhFk;. ,r;nraiyepiwNtw;w KbAkhd egNu gaDWjpAs;s njhopyhsu; Mthu;.",
    "fonts": [
      "Kalaham"
    ],
    "sizes": [
      12.000008583068848
    ]
  },
  {
    "page_number": 11,
    "bbox": [
      189.95,
      349.93,
      404.93,
      367.44
    ],
    "text": "6.3 nraw;wpwd; kw;Wk; gaDWjp6.3 nraw;wpwd; kw;Wk; gaDWjp6.3 nraw;wpwd; kw;Wk; gaDWjp6.3 nraw;wpwd; kw;Wk; gaDWjp6.3 nraw;wpwd; kw;Wk; gaDWjp",
    "fonts": [
      "Kalyani"
    ],
    "sizes": [
      17.000011444091797
    ]
  },
  {
    "page_number": 11,
    "bbox": [
      108.48,
      378.57,
      486.47,
      406.53
    ],
    "text": "nraw;wpwd; kw;Wk; gaDWjp vd;gd ,d;iwa Ntiy cyfpy;mjpfkhfg; gad;gLj;Jfpd;w ,U vz;zf;fUf;fshFk;.",
    "fonts": [
      "Kalaham"
    ],
    "sizes": [
      12.000008583068848
    ]
  },
  {
    "page_number": 11,
    "bbox": [
      122.88,
      423.68,
      472.01,
      470.61
    ],
    "text": "\u2666nraw;wpwd; vd;gJ ~~ fpilf;fg; ngWfpd;w tsq;fis cr;rmstpy; gad;gLj;jp xU nghUis cw;gj;jp nra;jy; my;yJxU Nritia toq;FtjhFk;||",
    "fonts": [
      "Kalaham",
      "Symbol"
    ],
    "sizes": [
      12.000008583068848
    ]
  },
  {
    "page_number": 11,
    "bbox": [
      122.88,
      479.72,
      472.05,
      526.53
    ],
    "text": "\u2666gaDWjp vd;gJ mjpf nraw;wpwDld; nraw;gl;L epWtdj;jpd;Nehf;fk; kw;Wk; mjDld; njhlu;ghd Njitfis mile;Jnfhs;tjhFk;.",
    "fonts": [
      "Kalaham",
      "Symbol"
    ],
    "sizes": [
      12.000008583068848
    ]
  },
  {
    "page_number": 11,
    "bbox": [
      108.48,
      546.57,
      486.69,
      590.61
    ],
    "text": "xU epWtdj;jpd; gaDWjpahdJ mq;F flikapy; <LgLfpd;wnjhopyhsu;fspd; tpidj;jpwdpYk; (nraw;wpwd;) epWtd Kfhikj;Jtj;jpd;nraw;wpwdpYk; jq;fp ,Uf;fpd;wJ.",
    "fonts": [
      "Kalaham"
    ],
    "sizes": [
      12.000008583068848
    ]
  },
  {
    "page_number": 11,
    "bbox": [
      108.48,
      602.61,
      486.46,
      630.57
    ],
    "text": "njhopyhsu;fspd; nraw;wpwd; kw;Wk; gaDWjpia Nkk;gLj;Jtjw;FfPo;tUk; tplaq;fs; cjtpahf mikfpd;wd.",
    "fonts": [
      "Kalaham"
    ],
    "sizes": [
      12.000008583068848
    ]
  },
  {
    "page_number": 11,
    "bbox": [
      122.88,
      647.72,
      460.17,
      678.57
    ],
    "text": "\u2666jdJ Mw;wy;fis tsu;j;Jf; nfhs;Sk; Nehf;Fld; flikGupAk; mNj Ntis gapw;rpfspYk; <Lgly;.",
    "fonts": [
      "Kalaham",
      "Symbol"
    ],
    "sizes": [
      12.000008583068848
    ]
  },
  {
    "page_number": 12,
    "bbox": [
      291.48,
      720.93,
      486.47,
      740.36
    ],
    "text": "13,ytr ghlE}y; tpepNahfj;jpw;fhf",
    "fonts": [
      "Kalaham",
      "Times-Roman"
    ],
    "sizes": [
      9.000006675720215,
      12.000008583068848
    ]
  },
  {
    "page_number": 12,
    "bbox": [
      117.48,
      131.72,
      472.07,
      226.53
    ],
    "text": "\u2666rk fhyj;jpy; ve;jnthU NtiyapidAk; mtrukhfTk;>rupahfTk; nra;tjw;F fzpdpg; ghtid njhlu;ghd mwpTkpf Kf;fpakhdjhFk;. NkYk; Mq;fpy nkhop njhlu;ghdMw;wiyAk; tsu;j;Jf; nfhs;tjd; %ykhfNt> jhd; nra;fpd;wfhupaq;fis kpfTk; gaDWjpAld; nra;tjw;F Mw;wy;fpilf;Fk;.",
    "fonts": [
      "Kalaham",
      "Symbol"
    ],
    "sizes": [
      12.000008583068848
    ]
  },
  {
    "page_number": 12,
    "bbox": [
      216.3,
      246.39,
      469.37,
      290.47
    ],
    "text": "Njrpa jfty; njhopDl;gk; kw;Wk; Mq;fpyNjrpa jfty; njhopDl;gk; kw;Wk; Mq;fpyNjrpa jfty; njhopDl;gk; kw;Wk; Mq;fpyNjrpa jfty; njhopDl;gk; kw;Wk; Mq;fpyNjrpa jfty; njhopDl;gk; kw;Wk; Mq;fpyfy;tpahz;Lfy;tpahz;Lfy;tpahz;Lfy;tpahz;Lfy;tpahz;L(Year of ICT & English Education)",
    "fonts": [
      "Kalaham",
      "Times-Bold"
    ],
    "sizes": [
      12.000008583068848
    ]
  },
  {
    "page_number": 12,
    "bbox": [
      117.48,
      307.64,
      472.08,
      370.53
    ],
    "text": "\u2666njhopy; Ma;T kw;Wk; gFg;gha;Tfspy; <LgLtjd; %yk;> jhd;nra;fpd;w fUkq;fis kpfr; rpwg;ghfTk;> nraw;wpwDlDk;nra;a KbAkhd topKiwfs; njhlu;ghf mwptpidg; ngwKbAk;.",
    "fonts": [
      "Kalaham",
      "Symbol"
    ],
    "sizes": [
      12.000008583068848
    ]
  },
  {
    "page_number": 12,
    "bbox": [
      117.48,
      379.64,
      472.04,
      410.61
    ],
    "text": "\u2666ngw;Wf; nfhs;fpd;w rk;gsj;ij tpl jhd; nra;fpd;w nraypd;juk; njhlu;ghff; $ba ftdk; vLj;jy; Ntz;Lk;.",
    "fonts": [
      "Kalaham",
      "Symbol"
    ],
    "sizes": [
      12.000008583068848
    ]
  },
  {
    "page_number": 12,
    "bbox": [
      117.48,
      419.72,
      472.09,
      514.53
    ],
    "text": "\u2666jpl;lkpl;L nraw;gLj;Jtjw;fhd Ie;J v]; (5S) vz;zf;fUNghd;w Kiwfs; njhlu;ghf mwpe;J nfhs;tjd; %ykhfTk;mtw;iw G+uzkhfg; gpd;gw;Wtjd; %ykhfTk; xU epWtdk;nray;jpwd;kpf;fjhfr; nraw;gl cjt KbAk;. [g;ghdpd; 5Svz;zf;fUthdJ epWtdq;fspd; nray;jpwid Nkk;gLj;Jtjw;nfd rkfhyj;jpy; gad;gLj;jg;gLk; xU nrad;KiwahFk;.",
    "fonts": [
      "Kalaham",
      "Symbol",
      "Times-Roman"
    ],
    "sizes": [
      12.000008583068848
    ]
  },
  {
    "page_number": 12,
    "bbox": [
      124.47,
      564.06,
      155.58,
      604.64
    ],
    "text": "Nju;e;njLj;jy;",
    "fonts": [
      "Kalaham"
    ],
    "sizes": [
      6.999936580657959,
      8.999908447265625
    ]
  },
  {
    "page_number": 12,
    "bbox": [
      219.4,
      567.93,
      250.72,
      599.58
    ],
    "text": "xOq;FgLj;jy;",
    "fonts": [
      "Kalaham"
    ],
    "sizes": [
      7.999917030334473
    ]
  },
  {
    "page_number": 12,
    "bbox": [
      169.08,
      609.56,
      208.07,
      630.56
    ],
    "text": "Rafl;Lg;ghL",
    "fonts": [
      "Kalaham"
    ],
    "sizes": [
      9.000006675720215
    ]
  },
  {
    "page_number": 12,
    "bbox": [
      216.83,
      643.43,
      237.33,
      663.93
    ],
    "text": "Rj;jk;",
    "fonts": [
      "Kalaham"
    ],
    "sizes": [
      7.999927520751953
    ]
  },
  {
    "page_number": 12,
    "bbox": [
      223.02,
      649.72,
      250.9,
      677.59
    ],
    "text": "NgZjy;",
    "fonts": [
      "Kalaham"
    ],
    "sizes": [
      7.999927520751953
    ]
  },
  {
    "page_number": 12,
    "bbox": [
      124.17,
      636.74,
      164.02,
      676.77
    ],
    "text": "xOq;Ffisgpd;gw;wy;",
    "fonts": [
      "Kalaham"
    ],
    "sizes": [
      7.999927520751953,
      8.999919891357422
    ]
  },
  {
    "page_number": 12,
    "bbox": [
      124.5,
      538.35,
      345.41,
      550.71
    ],
    "text": "[g;ghdpd; [g;ghdpd; [g;ghdpd; [g;ghdpd; [g;ghdpd; 5S vz;zf;fU gpd;tUkhW vz;zf;fU gpd;tUkhW vz;zf;fU gpd;tUkhW vz;zf;fU gpd;tUkhW vz;zf;fU gpd;tUkhW",
    "fonts": [
      "Kalaham",
      "Times-Bold"
    ],
    "sizes": [
      12.000008583068848
    ]
  },
  {
    "page_number": 12,
    "bbox": [
      268.44,
      553.99,
      475.21,
      622.04
    ],
    "text": "Nju;e;njLj;jy;- mdhtrpakhdtw;iw ePf;Fjy;xOq;FgLj;jy;- mtrpakhdtw;iw xOq;FKiwapy; itj;jy;Rj;jk; NgZjy; - Ntiynra;Ak; #oiy mOf;fpd;wpg; NgZjy;",
    "fonts": [
      "FMAbhaya",
      "Kalaham"
    ],
    "sizes": [
      10.000007629394531
    ]
  },
  {
    "page_number": 12,
    "bbox": [
      268.44,
      625.99,
      474.81,
      666.08
    ],
    "text": "xOq;Ffisg; gpd;gw;wy; - epWtdj;jpd; xOq;F kw;Wk; Rj;jj;jpidj; njhlu;e;J ghJfhj;jy;",
    "fonts": [
      "FMAbhaya",
      "Kalaham"
    ],
    "sizes": [
      10.000007629394531
    ]
  },
  {
    "page_number": 12,
    "bbox": [
      268.44,
      669.91,
      455.89,
      707.48
    ],
    "text": "Ra fl;LghL- ,r;rl;ljpl;lq;fisAk; xOq;FfisAk; tho;ehs; KOJk; filg;gpbj;jy;",
    "fonts": [
      "FMAbhaya",
      "Kalaham"
    ],
    "sizes": [
      10.000007629394531
    ]
  },
  {
    "page_number": 12,
    "bbox": [
      129.62,
      240.83,
      192.59,
      281.0
    ],
    "text": "20092009200920092009",
    "fonts": [
      "Kalaham"
    ],
    "sizes": [
      39.00002670288086
    ]
  },
  {
    "page_number": 13,
    "bbox": [
      108.48,
      720.93,
      303.48,
      740.36
    ],
    "text": "14,ytr ghlE}y; tpepNahfj;jpw;fhf",
    "fonts": [
      "Kalaham",
      "Times-Roman"
    ],
    "sizes": [
      9.000006675720215,
      12.000008583068848
    ]
  },
  {
    "page_number": 13,
    "bbox": [
      108.48,
      134.61,
      486.6,
      226.53
    ],
    "text": "jpl;lkpl;l Kfhikj;JtkhdJ xU epWtdj;jpd; nray;jpwdpy; ghupanry;thf;ifr; nrYj;Jfpd;wJ. epWtdj;jpd; Kfhikahsu;fs;xOq;fikg;GlDk;> jpl;lkpl;l mbg;gilapYk; nraw;gLtJ> epWtdj;jpd;nray;jpwid Nkk;gLj;jf; fhuzkhfpd;wJ. mt;thNw Copau; eyd;Gupeltbf;iffSk;> epWtdj;jpd; nray;jpwd; Nkk;ghl;by; gq;fspg;Gr; nra;Ak;Kf;fpa fhuzpfshFk;.",
    "fonts": [
      "Kalaham"
    ],
    "sizes": [
      12.000008583068848
    ]
  },
  {
    "page_number": 13,
    "bbox": [
      108.48,
      389.44,
      168.7,
      403.86
    ],
    "text": "nraw;ghLnraw;ghLnraw;ghLnraw;ghLnraw;ghL",
    "fonts": [
      "Kalaham",
      "Kalyani"
    ],
    "sizes": [
      12.000008583068848,
      14.000009536743164
    ]
  },
  {
    "page_number": 13,
    "bbox": [
      122.88,
      422.61,
      472.06,
      466.53
    ],
    "text": "epWtdnkhd;wpd; nraw;wpwid mjpfupg;gjw;F gad;gLj;j KbAkhdKiwik njhlu;ghf (rpe;jidf; fpsu;T) fye;Jiuahly; xd;wpy;<LgLq;fs;.",
    "fonts": [
      "Kalaham"
    ],
    "sizes": [
      12.000008583068848
    ]
  },
  {
    "page_number": 13,
    "bbox": [
      132.24,
      239.92,
      210.23,
      274.28
    ],
    "text": "nraw;wpwDk;Cf;fKk; nfhz;lNritazp",
    "fonts": [
      "Kalaham"
    ],
    "sizes": [
      10.000007629394531
    ]
  },
  {
    "page_number": 13,
    "bbox": [
      265.32,
      242.2,
      471.83,
      276.56
    ],
    "text": "epWtdj;jpd;,yf;if miljy;nraw;wpwDk;>Cf;fKk; nfhz;lKfhikahsu;fs;.",
    "fonts": [
      "Kalaham"
    ],
    "sizes": [
      10.000007629394531
    ]
  },
  {
    "page_number": 13,
    "bbox": [
      265.29,
      329.17,
      350.31,
      351.71
    ],
    "text": "nraw;wpwd;nraw;wpwd;nraw;wpwd;nraw;wpwd;nraw;wpwd;nfhz;l epWtdk;nfhz;l epWtdk;nfhz;l epWtdk;nfhz;l epWtdk;nfhz;l epWtdk;",
    "fonts": [
      "Kalaham"
    ],
    "sizes": [
      10.000007629394531
    ]
  },
  {
    "page_number": 14,
    "bbox": [
      291.48,
      720.93,
      486.47,
      740.36
    ],
    "text": "15,ytr ghlE}y; tpepNahfj;jpw;fhf",
    "fonts": [
      "Kalaham",
      "Times-Roman"
    ],
    "sizes": [
      9.000006675720215,
      12.000008583068848
    ]
  },
  {
    "page_number": 14,
    "bbox": [
      108.27,
      138.52,
      169.4,
      152.94
    ],
    "text": "rhuhk;rk; rhuhk;rk; rhuhk;rk; rhuhk;rk; rhuhk;rk;",
    "fonts": [
      "Kalyani"
    ],
    "sizes": [
      14.000009536743164
    ]
  },
  {
    "page_number": 14,
    "bbox": [
      119.76,
      168.8,
      472.04,
      183.69
    ],
    "text": "\u2666rkfhy Ntiy cyfhdJ tpupthf tpahgpj;Jf; fhzg;gLfpd;wJ.",
    "fonts": [
      "Kalaham",
      "Symbol"
    ],
    "sizes": [
      12.000008583068848
    ]
  },
  {
    "page_number": 14,
    "bbox": [
      119.76,
      204.8,
      472.2,
      251.61
    ],
    "text": "\u2666Ntiy cyfpw;Fs; gpuNtrpf;fpd;w xUtu; Ntiy cyfpDs;fhzg;gLfpd;w gy;NtWgl;l njhopy;fs; njhlu;ghf mwpe;jpUj;jy;kpf Kf;fpakhdjhFk;.",
    "fonts": [
      "Kalaham",
      "Symbol"
    ],
    "sizes": [
      12.000008583068848
    ]
  },
  {
    "page_number": 14,
    "bbox": [
      119.76,
      272.72,
      472.03,
      319.65
    ],
    "text": "\u2666njhopy; Jiw xd;iwj; Nju;e;njLf;Fk;NghJ jdJ <LghL>Mw;wy;fs; kw;Wk; vjpu;ghu;g;Gf;fs; njhlu;ghff; ftdk;nrYj;Jjy; Ntz;Lk;.",
    "fonts": [
      "Kalaham",
      "Symbol"
    ],
    "sizes": [
      12.000008583068848
    ]
  },
  {
    "page_number": 14,
    "bbox": [
      119.76,
      340.76,
      472.0,
      371.61
    ],
    "text": "\u2666njhopy; xd;Wf;Fj; Njitahd mbg;gilj; Nju;r;rpiag;ngWtjw;F njhopw;gapw;rp kpf Kf;fpakhFk;.",
    "fonts": [
      "Kalaham",
      "Symbol"
    ],
    "sizes": [
      12.000008583068848
    ]
  },
  {
    "page_number": 14,
    "bbox": [
      119.76,
      392.72,
      472.05,
      423.69
    ],
    "text": "\u2666njhopw; gapw;rpapid kpfg; gaDs;sjhf;Ftjw;F murpd; %yk;tpNrl epWtdr; rl;lfk; xd;W cUthf;fg;gl;Ls;sJ.",
    "fonts": [
      "Kalaham",
      "Symbol"
    ],
    "sizes": [
      12.000008583068848
    ]
  },
  {
    "page_number": 14,
    "bbox": [
      119.76,
      444.68,
      472.06,
      491.61
    ],
    "text": "\u2666xU epWtdj;jpd; nraw;wpwd; Nkk;ghl;bw;F me; epWtdj;jpdhy;Ntiy nfhs;Nthu;> Ntiy nra;Nthu; Mfpa ,U ghyhupdJk;xj;Jiog;G kpf mtrpakhFk;.",
    "fonts": [
      "Kalaham",
      "Symbol"
    ],
    "sizes": [
      12.000008583068848
    ]
  },
  {
    "page_number": 14,
    "bbox": [
      108.27,
      526.48,
      164.96,
      540.9
    ],
    "text": "xg;gil xg;gil xg;gil xg;gil xg;gil",
    "fonts": [
      "Kalyani"
    ],
    "sizes": [
      14.000009536743164
    ]
  },
  {
    "page_number": 14,
    "bbox": [
      122.7,
      558.57,
      472.06,
      628.17
    ],
    "text": "njhopy; topfhl;ly; myF xd;wpy; fz;fhl;rpg;gLj;Jtjw;fhf~~ckf;F xU njhopy; - ehl;Lf;nfhU Nrit||~~ckf;F xU njhopy; - ehl;Lf;nfhU Nrit||~~ckf;F xU njhopy; - ehl;Lf;nfhU Nrit||~~ckf;F xU njhopy; - ehl;Lf;nfhU Nrit||~~ckf;F xU njhopy; - ehl;Lf;nfhU Nrit|| vd;w fUj;Jg;glRtnuhl;bnahd;iwj; jahupf;fTk;. njhopy; Jiw xd;iwj; njupTnra;Ak;NghJ mtrpakhd midj;J tplaq;fSk; ,jpy; cs;slf;fg;gl;bUj;jy; mtrpak;.",
    "fonts": [
      "Kalaham"
    ],
    "sizes": [
      12.000008583068848
    ]
  }
]