{
  "doc_type": "lk_edupub",
  "doc_id": "2025-01-01-7-en-753-grade-7-en-geo-1827b313",
  "num": "7-en-753-grade-7-en-geography-2016-new-syllabus-03-the-landscape-of-sri-lanka",
  "date_str": "2025-01-01",
  "description": "(Grade 7/en) Geography - 2016 New Syllabus  - 03 The landscape of Sri Lanka",
  "url_metadata": "http://www.edupub.gov.lk/SelectChapter.php",
  "lang": "en",
  "url_pdf": "http://www.edupub.gov.lk/Administrator/English/7/Geography G 7( E)/c3.pdf",
  "grade_id": 7,
  "book_id": "753",
  "book_name": "Geography - 2016 New Syllabus ",
  "chapter_name": "03 The landscape of Sri Lanka"
}